{ "SolutionInfo": { "Status": 9, "Runtime": 1.3890000104904175e+01, "Work": 7.2610832182462426e+00, "ObjVal": 312, "ObjBound": 351, "ObjBoundC": 351, "MIPGap": 0.125, "IntVio": 0, "BoundVio": 0, "ConstrVio": 0, "IterCount": 277875, "BarIterCount": 0, "NodeCount": 1, "SolCount": 1, "PoolObjBound": 351, "PoolObjVal": [ 312]}, "Vars": [ { "VarName": "meets[girl_0,girl_1]", "X": 1}, { "VarName": "meets[girl_0,girl_2]", "X": 1}, { "VarName": "meets[girl_0,girl_3]", "X": 1}, { "VarName": "meets[girl_0,girl_4]", "X": 1}, { "VarName": "meets[girl_0,girl_5]", "X": 1}, { "VarName": "meets[girl_0,girl_6]", "X": 1}, { "VarName": "meets[girl_0,girl_7]", "X": 1}, { "VarName": "meets[girl_0,girl_8]", "X": 1}, { "VarName": "meets[girl_0,girl_9]", "X": 1}, { "VarName": "meets[girl_0,girl_10]", "X": 1}, { "VarName": "meets[girl_0,girl_11]", "X": 1}, { "VarName": "meets[girl_0,girl_12]", "X": 1}, { "VarName": "meets[girl_0,boy_0]", "X": 1}, { "VarName": "meets[girl_0,boy_1]", "X": 1}, { "VarName": "meets[girl_0,boy_2]", "X": 1}, { "VarName": "meets[girl_0,boy_3]", "X": 1}, { "VarName": "meets[girl_0,boy_4]", "X": 1}, { "VarName": "meets[girl_0,boy_5]", "X": 1}, { "VarName": "meets[girl_0,boy_6]", "X": 1}, { "VarName": "meets[girl_0,boy_7]", "X": 1}, { "VarName": "meets[girl_0,boy_8]", "X": 1}, { "VarName": "meets[girl_0,boy_9]", "X": 1}, { "VarName": "meets[girl_0,boy_10]", "X": 1}, { "VarName": "meets[girl_0,boy_12]", "X": 1}, { "VarName": "meets[girl_0,boy_13]", "X": 1}, { "VarName": "meets[girl_1,girl_2]", "X": 1}, { "VarName": "meets[girl_1,girl_3]", "X": 1}, { "VarName": "meets[girl_1,girl_4]", "X": 1}, { "VarName": "meets[girl_1,girl_5]", "X": 1}, { "VarName": "meets[girl_1,girl_6]", "X": 1}, { "VarName": "meets[girl_1,girl_7]", "X": 1}, { "VarName": "meets[girl_1,girl_8]", "X": 1}, { "VarName": "meets[girl_1,girl_9]", "X": 1}, { "VarName": "meets[girl_1,girl_10]", "X": 1}, { "VarName": "meets[girl_1,girl_11]", "X": 1}, { "VarName": "meets[girl_1,girl_12]", "X": 1}, { "VarName": "meets[girl_1,boy_0]", "X": 1}, { "VarName": "meets[girl_1,boy_1]", "X": 1}, { "VarName": "meets[girl_1,boy_2]", "X": 1}, { "VarName": "meets[girl_1,boy_4]", "X": 1}, { "VarName": "meets[girl_1,boy_5]", "X": 1}, { "VarName": "meets[girl_1,boy_6]", "X": 1}, { "VarName": "meets[girl_1,boy_7]", "X": 1}, { "VarName": "meets[girl_1,boy_8]", "X": 1}, { "VarName": "meets[girl_1,boy_9]", "X": 1}, { "VarName": "meets[girl_1,boy_10]", "X": 1}, { "VarName": "meets[girl_1,boy_11]", "X": 1}, { "VarName": "meets[girl_1,boy_12]", "X": 1}, { "VarName": "meets[girl_1,boy_13]", "X": 1}, { "VarName": "meets[girl_2,girl_3]", "X": 1}, { "VarName": "meets[girl_2,girl_4]", "X": 1}, { "VarName": "meets[girl_2,girl_5]", "X": 1}, { "VarName": "meets[girl_2,girl_6]", "X": 1}, { "VarName": "meets[girl_2,girl_7]", "X": 1}, { "VarName": "meets[girl_2,girl_8]", "X": 1}, { "VarName": "meets[girl_2,girl_10]", "X": 1}, { "VarName": "meets[girl_2,girl_11]", "X": 1}, { "VarName": "meets[girl_2,girl_12]", "X": 1}, { "VarName": "meets[girl_2,boy_0]", "X": 1}, { "VarName": "meets[girl_2,boy_1]", "X": 1}, { "VarName": "meets[girl_2,boy_2]", "X": 1}, { "VarName": "meets[girl_2,boy_3]", "X": 1}, { "VarName": "meets[girl_2,boy_4]", "X": 1}, { "VarName": "meets[girl_2,boy_5]", "X": 1}, { "VarName": "meets[girl_2,boy_8]", "X": 1}, { "VarName": "meets[girl_2,boy_9]", "X": 1}, { "VarName": "meets[girl_2,boy_10]", "X": 1}, { "VarName": "meets[girl_2,boy_11]", "X": 1}, { "VarName": "meets[girl_2,boy_12]", "X": 1}, { "VarName": "meets[girl_2,boy_13]", "X": 1}, { "VarName": "meets[girl_3,girl_5]", "X": 1}, { "VarName": "meets[girl_3,girl_6]", "X": 1}, { "VarName": "meets[girl_3,girl_7]", "X": 1}, { "VarName": "meets[girl_3,girl_8]", "X": 1}, { "VarName": "meets[girl_3,girl_9]", "X": 1}, { "VarName": "meets[girl_3,girl_10]", "X": 1}, { "VarName": "meets[girl_3,girl_11]", "X": 1}, { "VarName": "meets[girl_3,boy_0]", "X": 1}, { "VarName": "meets[girl_3,boy_2]", "X": 1}, { "VarName": "meets[girl_3,boy_3]", "X": 1}, { "VarName": "meets[girl_3,boy_4]", "X": 1}, { "VarName": "meets[girl_3,boy_6]", "X": 1}, { "VarName": "meets[girl_3,boy_7]", "X": 1}, { "VarName": "meets[girl_3,boy_8]", "X": 1}, { "VarName": "meets[girl_3,boy_9]", "X": 1}, { "VarName": "meets[girl_3,boy_10]", "X": 1}, { "VarName": "meets[girl_3,boy_11]", "X": 1}, { "VarName": "meets[girl_3,boy_12]", "X": 1}, { "VarName": "meets[girl_3,boy_13]", "X": 1}, { "VarName": "meets[girl_4,girl_6]", "X": 1}, { "VarName": "meets[girl_4,girl_8]", "X": 1}, { "VarName": "meets[girl_4,girl_9]", "X": 1}, { "VarName": "meets[girl_4,girl_10]", "X": 1}, { "VarName": "meets[girl_4,girl_11]", "X": 1}, { "VarName": "meets[girl_4,girl_12]", "X": 1}, { "VarName": "meets[girl_4,boy_0]", "X": 1}, { "VarName": "meets[girl_4,boy_1]", "X": 1}, { "VarName": "meets[girl_4,boy_2]", "X": 1}, { "VarName": "meets[girl_4,boy_3]", "X": 1}, { "VarName": "meets[girl_4,boy_4]", "X": 1}, { "VarName": "meets[girl_4,boy_5]", "X": 1}, { "VarName": "meets[girl_4,boy_6]", "X": 1}, { "VarName": "meets[girl_4,boy_7]", "X": 1}, { "VarName": "meets[girl_4,boy_8]", "X": 1}, { "VarName": "meets[girl_4,boy_9]", "X": 1}, { "VarName": "meets[girl_4,boy_10]", "X": 1}, { "VarName": "meets[girl_4,boy_11]", "X": 1}, { "VarName": "meets[girl_4,boy_12]", "X": 1}, { "VarName": "meets[girl_4,boy_13]", "X": 1}, { "VarName": "meets[girl_5,girl_6]", "X": 1}, { "VarName": "meets[girl_5,girl_7]", "X": 1}, { "VarName": "meets[girl_5,girl_8]", "X": 1}, { "VarName": "meets[girl_5,girl_9]", "X": 1}, { "VarName": "meets[girl_5,girl_11]", "X": 1}, { "VarName": "meets[girl_5,girl_12]", "X": 1}, { "VarName": "meets[girl_5,boy_0]", "X": 1}, { "VarName": "meets[girl_5,boy_2]", "X": 1}, { "VarName": "meets[girl_5,boy_3]", "X": 1}, { "VarName": "meets[girl_5,boy_4]", "X": 1}, { "VarName": "meets[girl_5,boy_5]", "X": 1}, { "VarName": "meets[girl_5,boy_6]", "X": 1}, { "VarName": "meets[girl_5,boy_7]", "X": 1}, { "VarName": "meets[girl_5,boy_8]", "X": 1}, { "VarName": "meets[girl_5,boy_9]", "X": 1}, { "VarName": "meets[girl_5,boy_10]", "X": 1}, { "VarName": "meets[girl_5,boy_11]", "X": 1}, { "VarName": "meets[girl_5,boy_12]", "X": 1}, { "VarName": "meets[girl_5,boy_13]", "X": 1}, { "VarName": "meets[girl_6,girl_7]", "X": 1}, { "VarName": "meets[girl_6,girl_10]", "X": 1}, { "VarName": "meets[girl_6,girl_11]", "X": 1}, { "VarName": "meets[girl_6,girl_12]", "X": 1}, { "VarName": "meets[girl_6,boy_0]", "X": 1}, { "VarName": "meets[girl_6,boy_1]", "X": 1}, { "VarName": "meets[girl_6,boy_2]", "X": 1}, { "VarName": "meets[girl_6,boy_3]", "X": 1}, { "VarName": "meets[girl_6,boy_4]", "X": 1}, { "VarName": "meets[girl_6,boy_5]", "X": 1}, { "VarName": "meets[girl_6,boy_6]", "X": 1}, { "VarName": "meets[girl_6,boy_7]", "X": 1}, { "VarName": "meets[girl_6,boy_9]", "X": 1}, { "VarName": "meets[girl_6,boy_10]", "X": 1}, { "VarName": "meets[girl_6,boy_11]", "X": 1}, { "VarName": "meets[girl_6,boy_12]", "X": 1}, { "VarName": "meets[girl_6,boy_13]", "X": 1}, { "VarName": "meets[girl_7,girl_8]", "X": 1}, { "VarName": "meets[girl_7,girl_9]", "X": 1}, { "VarName": "meets[girl_7,girl_11]", "X": 1}, { "VarName": "meets[girl_7,girl_12]", "X": 1}, { "VarName": "meets[girl_7,boy_0]", "X": 1}, { "VarName": "meets[girl_7,boy_1]", "X": 1}, { "VarName": "meets[girl_7,boy_2]", "X": 1}, { "VarName": "meets[girl_7,boy_3]", "X": 1}, { "VarName": "meets[girl_7,boy_4]", "X": 1}, { "VarName": "meets[girl_7,boy_5]", "X": 1}, { "VarName": "meets[girl_7,boy_6]", "X": 1}, { "VarName": "meets[girl_7,boy_7]", "X": 1}, { "VarName": "meets[girl_7,boy_8]", "X": 1}, { "VarName": "meets[girl_7,boy_9]", "X": 1}, { "VarName": "meets[girl_7,boy_10]", "X": 1}, { "VarName": "meets[girl_7,boy_11]", "X": 1}, { "VarName": "meets[girl_7,boy_12]", "X": 1}, { "VarName": "meets[girl_7,boy_13]", "X": 1}, { "VarName": "meets[girl_8,girl_9]", "X": 1}, { "VarName": "meets[girl_8,girl_10]", "X": 1}, { "VarName": "meets[girl_8,girl_11]", "X": 1}, { "VarName": "meets[girl_8,girl_12]", "X": 1}, { "VarName": "meets[girl_8,boy_0]", "X": 1}, { "VarName": "meets[girl_8,boy_1]", "X": 1}, { "VarName": "meets[girl_8,boy_2]", "X": 1}, { "VarName": "meets[girl_8,boy_3]", "X": 1}, { "VarName": "meets[girl_8,boy_4]", "X": 1}, { "VarName": "meets[girl_8,boy_5]", "X": 1}, { "VarName": "meets[girl_8,boy_6]", "X": 1}, { "VarName": "meets[girl_8,boy_7]", "X": 1}, { "VarName": "meets[girl_8,boy_8]", "X": 1}, { "VarName": "meets[girl_8,boy_9]", "X": 1}, { "VarName": "meets[girl_8,boy_10]", "X": 1}, { "VarName": "meets[girl_8,boy_11]", "X": 1}, { "VarName": "meets[girl_8,boy_12]", "X": 1}, { "VarName": "meets[girl_8,boy_13]", "X": 1}, { "VarName": "meets[girl_9,girl_10]", "X": 1}, { "VarName": "meets[girl_9,girl_12]", "X": 1}, { "VarName": "meets[girl_9,boy_0]", "X": 1}, { "VarName": "meets[girl_9,boy_1]", "X": 1}, { "VarName": "meets[girl_9,boy_2]", "X": 1}, { "VarName": "meets[girl_9,boy_4]", "X": 1}, { "VarName": "meets[girl_9,boy_5]", "X": 1}, { "VarName": "meets[girl_9,boy_6]", "X": 1}, { "VarName": "meets[girl_9,boy_7]", "X": 1}, { "VarName": "meets[girl_9,boy_8]", "X": 1}, { "VarName": "meets[girl_9,boy_9]", "X": 1}, { "VarName": "meets[girl_9,boy_10]", "X": 1}, { "VarName": "meets[girl_9,boy_11]", "X": 1}, { "VarName": "meets[girl_9,boy_12]", "X": 1}, { "VarName": "meets[girl_9,boy_13]", "X": 1}, { "VarName": "meets[girl_10,girl_11]", "X": 1}, { "VarName": "meets[girl_10,girl_12]", "X": 1}, { "VarName": "meets[girl_10,boy_0]", "X": 1}, { "VarName": "meets[girl_10,boy_2]", "X": 1}, { "VarName": "meets[girl_10,boy_3]", "X": 1}, { "VarName": "meets[girl_10,boy_4]", "X": 1}, { "VarName": "meets[girl_10,boy_5]", "X": 1}, { "VarName": "meets[girl_10,boy_6]", "X": 1}, { "VarName": "meets[girl_10,boy_7]", "X": 1}, { "VarName": "meets[girl_10,boy_8]", "X": 1}, { "VarName": "meets[girl_10,boy_9]", "X": 1}, { "VarName": "meets[girl_10,boy_10]", "X": 1}, { "VarName": "meets[girl_10,boy_11]", "X": 1}, { "VarName": "meets[girl_10,boy_12]", "X": 1}, { "VarName": "meets[girl_10,boy_13]", "X": 1}, { "VarName": "meets[girl_11,girl_12]", "X": 1}, { "VarName": "meets[girl_11,boy_0]", "X": 1}, { "VarName": "meets[girl_11,boy_1]", "X": 1}, { "VarName": "meets[girl_11,boy_2]", "X": 1}, { "VarName": "meets[girl_11,boy_3]", "X": 1}, { "VarName": "meets[girl_11,boy_4]", "X": 1}, { "VarName": "meets[girl_11,boy_5]", "X": 1}, { "VarName": "meets[girl_11,boy_6]", "X": 1}, { "VarName": "meets[girl_11,boy_7]", "X": 1}, { "VarName": "meets[girl_11,boy_8]", "X": 1}, { "VarName": "meets[girl_11,boy_9]", "X": 1}, { "VarName": "meets[girl_11,boy_10]", "X": 1}, { "VarName": "meets[girl_11,boy_11]", "X": 1}, { "VarName": "meets[girl_11,boy_12]", "X": 1}, { "VarName": "meets[girl_11,boy_13]", "X": 1}, { "VarName": "meets[girl_12,boy_1]", "X": 1}, { "VarName": "meets[girl_12,boy_2]", "X": 1}, { "VarName": "meets[girl_12,boy_4]", "X": 1}, { "VarName": "meets[girl_12,boy_5]", "X": 1}, { "VarName": "meets[girl_12,boy_6]", "X": 1}, { "VarName": "meets[girl_12,boy_7]", "X": 1}, { "VarName": "meets[girl_12,boy_8]", "X": 1}, { "VarName": "meets[girl_12,boy_9]", "X": 1}, { "VarName": "meets[girl_12,boy_10]", "X": 1}, { "VarName": "meets[girl_12,boy_11]", "X": 1}, { "VarName": "meets[girl_12,boy_13]", "X": 1}, { "VarName": "meets[boy_0,boy_1]", "X": 1}, { "VarName": "meets[boy_0,boy_2]", "X": 1}, { "VarName": "meets[boy_0,boy_3]", "X": 1}, { "VarName": "meets[boy_0,boy_4]", "X": 1}, { "VarName": "meets[boy_0,boy_5]", "X": 1}, { "VarName": "meets[boy_0,boy_6]", "X": 1}, { "VarName": "meets[boy_0,boy_7]", "X": 1}, { "VarName": "meets[boy_0,boy_8]", "X": 1}, { "VarName": "meets[boy_0,boy_9]", "X": 1}, { "VarName": "meets[boy_0,boy_10]", "X": 1}, { "VarName": "meets[boy_0,boy_12]", "X": 1}, { "VarName": "meets[boy_0,boy_13]", "X": 1}, { "VarName": "meets[boy_1,boy_3]", "X": 1}, { "VarName": "meets[boy_1,boy_4]", "X": 1}, { "VarName": "meets[boy_1,boy_5]", "X": 1}, { "VarName": "meets[boy_1,boy_6]", "X": 1}, { "VarName": "meets[boy_1,boy_7]", "X": 1}, { "VarName": "meets[boy_1,boy_8]", "X": 1}, { "VarName": "meets[boy_1,boy_9]", "X": 1}, { "VarName": "meets[boy_1,boy_10]", "X": 1}, { "VarName": "meets[boy_1,boy_11]", "X": 1}, { "VarName": "meets[boy_1,boy_12]", "X": 1}, { "VarName": "meets[boy_2,boy_3]", "X": 1}, { "VarName": "meets[boy_2,boy_4]", "X": 1}, { "VarName": "meets[boy_2,boy_6]", "X": 1}, { "VarName": "meets[boy_2,boy_7]", "X": 1}, { "VarName": "meets[boy_2,boy_8]", "X": 1}, { "VarName": "meets[boy_2,boy_9]", "X": 1}, { "VarName": "meets[boy_2,boy_10]", "X": 1}, { "VarName": "meets[boy_2,boy_11]", "X": 1}, { "VarName": "meets[boy_2,boy_12]", "X": 1}, { "VarName": "meets[boy_2,boy_13]", "X": 1}, { "VarName": "meets[boy_3,boy_4]", "X": 1}, { "VarName": "meets[boy_3,boy_5]", "X": 1}, { "VarName": "meets[boy_3,boy_7]", "X": 1}, { "VarName": "meets[boy_3,boy_8]", "X": 1}, { "VarName": "meets[boy_3,boy_9]", "X": 1}, { "VarName": "meets[boy_3,boy_10]", "X": 1}, { "VarName": "meets[boy_3,boy_11]", "X": 1}, { "VarName": "meets[boy_3,boy_12]", "X": 1}, { "VarName": "meets[boy_3,boy_13]", "X": 1}, { "VarName": "meets[boy_4,boy_5]", "X": 1}, { "VarName": "meets[boy_4,boy_6]", "X": 1}, { "VarName": "meets[boy_4,boy_9]", "X": 1}, { "VarName": "meets[boy_4,boy_10]", "X": 1}, { "VarName": "meets[boy_4,boy_11]", "X": 1}, { "VarName": "meets[boy_4,boy_12]", "X": 1}, { "VarName": "meets[boy_5,boy_7]", "X": 1}, { "VarName": "meets[boy_5,boy_8]", "X": 1}, { "VarName": "meets[boy_5,boy_10]", "X": 1}, { "VarName": "meets[boy_5,boy_11]", "X": 1}, { "VarName": "meets[boy_5,boy_12]", "X": 1}, { "VarName": "meets[boy_5,boy_13]", "X": 1}, { "VarName": "meets[boy_6,boy_7]", "X": 1}, { "VarName": "meets[boy_6,boy_8]", "X": 1}, { "VarName": "meets[boy_6,boy_9]", "X": 1}, { "VarName": "meets[boy_6,boy_10]", "X": 1}, { "VarName": "meets[boy_6,boy_12]", "X": 1}, { "VarName": "meets[boy_6,boy_13]", "X": 1}, { "VarName": "meets[boy_7,boy_9]", "X": 1}, { "VarName": "meets[boy_7,boy_11]", "X": 1}, { "VarName": "meets[boy_7,boy_12]", "X": 1}, { "VarName": "meets[boy_7,boy_13]", "X": 1}, { "VarName": "meets[boy_8,boy_10]", "X": 1}, { "VarName": "meets[boy_8,boy_12]", "X": 1}, { "VarName": "meets[boy_8,boy_13]", "X": 1}, { "VarName": "meets[boy_9,boy_10]", "X": 1}, { "VarName": "meets[boy_9,boy_11]", "X": 1}, { "VarName": "meets[boy_9,boy_12]", "X": 1}, { "VarName": "meets[boy_9,boy_13]", "X": 1}, { "VarName": "meets[boy_10,boy_11]", "X": 1}, { "VarName": "meets[boy_10,boy_13]", "X": 1}, { "VarName": "meets[boy_11,boy_12]", "X": 1}, { "VarName": "meets[boy_11,boy_13]", "X": 1}, { "VarName": "meets[boy_12,boy_13]", "X": 1}, { "VarName": "meetsAtE[girl_0,girl_1,2]", "X": 1}, { "VarName": "meetsAtE[girl_0,girl_2,7]", "X": 1}, { "VarName": "meetsAtE[girl_0,girl_3,3]", "X": 1}, { "VarName": "meetsAtE[girl_0,girl_4,4]", "X": 1}, { "VarName": "meetsAtE[girl_0,girl_5,0]", "X": 1}, { "VarName": "meetsAtE[girl_0,girl_5,3]", "X": 1}, { "VarName": "meetsAtE[girl_0,girl_6,7]", "X": 1}, { "VarName": "meetsAtE[girl_0,girl_7,1]", "X": 1}, { "VarName": "meetsAtE[girl_0,girl_8,2]", "X": 1}, { "VarName": "meetsAtE[girl_0,girl_9,3]", "X": 1}, { "VarName": "meetsAtE[girl_0,girl_10,5]", "X": 1}, { "VarName": "meetsAtE[girl_0,girl_11,1]", "X": 1}, { "VarName": "meetsAtE[girl_0,girl_12,6]", "X": 1}, { "VarName": "meetsAtE[girl_0,boy_0,0]", "X": 1}, { "VarName": "meetsAtE[girl_0,boy_0,7]", "X": 1}, { "VarName": "meetsAtE[girl_0,boy_1,6]", "X": 1}, { "VarName": "meetsAtE[girl_0,boy_2,2]", "X": 1}, { "VarName": "meetsAtE[girl_0,boy_3,4]", "X": 1}, { "VarName": "meetsAtE[girl_0,boy_4,1]", "X": 1}, { "VarName": "meetsAtE[girl_0,boy_4,4]", "X": 1}, { "VarName": "meetsAtE[girl_0,boy_5,5]", "X": 1}, { "VarName": "meetsAtE[girl_0,boy_6,0]", "X": 1}, { "VarName": "meetsAtE[girl_0,boy_7,6]", "X": 1}, { "VarName": "meetsAtE[girl_0,boy_8,5]", "X": 1}, { "VarName": "meetsAtE[girl_0,boy_9,1]", "X": 1}, { "VarName": "meetsAtE[girl_0,boy_10,2]", "X": 1}, { "VarName": "meetsAtE[girl_0,boy_10,4]", "X": 1}, { "VarName": "meetsAtE[girl_0,boy_10,7]", "X": 1}, { "VarName": "meetsAtE[girl_0,boy_12,5]", "X": 1}, { "VarName": "meetsAtE[girl_0,boy_13,0]", "X": 1}, { "VarName": "meetsAtE[girl_1,girl_2,3]", "X": 1}, { "VarName": "meetsAtE[girl_1,girl_3,5]", "X": 1}, { "VarName": "meetsAtE[girl_1,girl_4,0]", "X": 1}, { "VarName": "meetsAtE[girl_1,girl_5,7]", "X": 1}, { "VarName": "meetsAtE[girl_1,girl_6,0]", "X": 1}, { "VarName": "meetsAtE[girl_1,girl_7,6]", "X": 1}, { "VarName": "meetsAtE[girl_1,girl_8,2]", "X": 1}, { "VarName": "meetsAtE[girl_1,girl_9,1]", "X": 1}, { "VarName": "meetsAtE[girl_1,girl_10,4]", "X": 1}, { "VarName": "meetsAtE[girl_1,girl_11,0]", "X": 1}, { "VarName": "meetsAtE[girl_1,girl_12,7]", "X": 1}, { "VarName": "meetsAtE[girl_1,boy_0,3]", "X": 1}, { "VarName": "meetsAtE[girl_1,boy_1,3]", "X": 1}, { "VarName": "meetsAtE[girl_1,boy_2,2]", "X": 1}, { "VarName": "meetsAtE[girl_1,boy_4,7]", "X": 1}, { "VarName": "meetsAtE[girl_1,boy_5,7]", "X": 1}, { "VarName": "meetsAtE[girl_1,boy_6,1]", "X": 1}, { "VarName": "meetsAtE[girl_1,boy_6,6]", "X": 1}, { "VarName": "meetsAtE[girl_1,boy_7,5]", "X": 1}, { "VarName": "meetsAtE[girl_1,boy_8,3]", "X": 1}, { "VarName": "meetsAtE[girl_1,boy_8,6]", "X": 1}, { "VarName": "meetsAtE[girl_1,boy_9,4]", "X": 1}, { "VarName": "meetsAtE[girl_1,boy_10,2]", "X": 1}, { "VarName": "meetsAtE[girl_1,boy_10,6]", "X": 1}, { "VarName": "meetsAtE[girl_1,boy_11,4]", "X": 1}, { "VarName": "meetsAtE[girl_1,boy_12,1]", "X": 1}, { "VarName": "meetsAtE[girl_1,boy_13,5]", "X": 1}, { "VarName": "meetsAtE[girl_2,girl_3,2]", "X": 1}, { "VarName": "meetsAtE[girl_2,girl_4,1]", "X": 1}, { "VarName": "meetsAtE[girl_2,girl_5,6]", "X": 1}, { "VarName": "meetsAtE[girl_2,girl_6,4]", "X": 1}, { "VarName": "meetsAtE[girl_2,girl_6,7]", "X": 1}, { "VarName": "meetsAtE[girl_2,girl_7,5]", "X": 1}, { "VarName": "meetsAtE[girl_2,girl_8,0]", "X": 1}, { "VarName": "meetsAtE[girl_2,girl_10,0]", "X": 1}, { "VarName": "meetsAtE[girl_2,girl_11,6]", "X": 1}, { "VarName": "meetsAtE[girl_2,girl_12,1]", "X": 1}, { "VarName": "meetsAtE[girl_2,boy_0,3]", "X": 1}, { "VarName": "meetsAtE[girl_2,boy_0,7]", "X": 1}, { "VarName": "meetsAtE[girl_2,boy_1,3]", "X": 1}, { "VarName": "meetsAtE[girl_2,boy_1,5]", "X": 1}, { "VarName": "meetsAtE[girl_2,boy_2,6]", "X": 1}, { "VarName": "meetsAtE[girl_2,boy_3,2]", "X": 1}, { "VarName": "meetsAtE[girl_2,boy_4,0]", "X": 1}, { "VarName": "meetsAtE[girl_2,boy_4,5]", "X": 1}, { "VarName": "meetsAtE[girl_2,boy_5,0]", "X": 1}, { "VarName": "meetsAtE[girl_2,boy_8,3]", "X": 1}, { "VarName": "meetsAtE[girl_2,boy_9,2]", "X": 1}, { "VarName": "meetsAtE[girl_2,boy_10,7]", "X": 1}, { "VarName": "meetsAtE[girl_2,boy_11,1]", "X": 1}, { "VarName": "meetsAtE[girl_2,boy_11,5]", "X": 1}, { "VarName": "meetsAtE[girl_2,boy_12,4]", "X": 1}, { "VarName": "meetsAtE[girl_2,boy_12,6]", "X": 1}, { "VarName": "meetsAtE[girl_2,boy_13,1]", "X": 1}, { "VarName": "meetsAtE[girl_2,boy_13,4]", "X": 1}, { "VarName": "meetsAtE[girl_3,girl_5,3]", "X": 1}, { "VarName": "meetsAtE[girl_3,girl_6,1]", "X": 1}, { "VarName": "meetsAtE[girl_3,girl_7,7]", "X": 1}, { "VarName": "meetsAtE[girl_3,girl_8,7]", "X": 1}, { "VarName": "meetsAtE[girl_3,girl_9,0]", "X": 1}, { "VarName": "meetsAtE[girl_3,girl_9,3]", "X": 1}, { "VarName": "meetsAtE[girl_3,girl_9,6]", "X": 1}, { "VarName": "meetsAtE[girl_3,girl_10,1]", "X": 1}, { "VarName": "meetsAtE[girl_3,girl_11,4]", "X": 1}, { "VarName": "meetsAtE[girl_3,boy_0,6]", "X": 1}, { "VarName": "meetsAtE[girl_3,boy_2,1]", "X": 1}, { "VarName": "meetsAtE[girl_3,boy_3,2]", "X": 1}, { "VarName": "meetsAtE[girl_3,boy_4,6]", "X": 1}, { "VarName": "meetsAtE[girl_3,boy_6,4]", "X": 1}, { "VarName": "meetsAtE[girl_3,boy_7,1]", "X": 1}, { "VarName": "meetsAtE[girl_3,boy_7,5]", "X": 1}, { "VarName": "meetsAtE[girl_3,boy_8,4]", "X": 1}, { "VarName": "meetsAtE[girl_3,boy_9,2]", "X": 1}, { "VarName": "meetsAtE[girl_3,boy_9,6]", "X": 1}, { "VarName": "meetsAtE[girl_3,boy_10,0]", "X": 1}, { "VarName": "meetsAtE[girl_3,boy_11,0]", "X": 1}, { "VarName": "meetsAtE[girl_3,boy_11,7]", "X": 1}, { "VarName": "meetsAtE[girl_3,boy_12,7]", "X": 1}, { "VarName": "meetsAtE[girl_3,boy_13,5]", "X": 1}, { "VarName": "meetsAtE[girl_4,girl_6,0]", "X": 1}, { "VarName": "meetsAtE[girl_4,girl_8,3]", "X": 1}, { "VarName": "meetsAtE[girl_4,girl_8,6]", "X": 1}, { "VarName": "meetsAtE[girl_4,girl_9,5]", "X": 1}, { "VarName": "meetsAtE[girl_4,girl_10,2]", "X": 1}, { "VarName": "meetsAtE[girl_4,girl_11,0]", "X": 1}, { "VarName": "meetsAtE[girl_4,girl_11,7]", "X": 1}, { "VarName": "meetsAtE[girl_4,girl_12,1]", "X": 1}, { "VarName": "meetsAtE[girl_4,boy_0,2]", "X": 1}, { "VarName": "meetsAtE[girl_4,boy_1,7]", "X": 1}, { "VarName": "meetsAtE[girl_4,boy_2,5]", "X": 1}, { "VarName": "meetsAtE[girl_4,boy_3,4]", "X": 1}, { "VarName": "meetsAtE[girl_4,boy_4,4]", "X": 1}, { "VarName": "meetsAtE[girl_4,boy_5,6]", "X": 1}, { "VarName": "meetsAtE[girl_4,boy_6,3]", "X": 1}, { "VarName": "meetsAtE[girl_4,boy_6,5]", "X": 1}, { "VarName": "meetsAtE[girl_4,boy_7,3]", "X": 1}, { "VarName": "meetsAtE[girl_4,boy_8,7]", "X": 1}, { "VarName": "meetsAtE[girl_4,boy_9,3]", "X": 1}, { "VarName": "meetsAtE[girl_4,boy_10,4]", "X": 1}, { "VarName": "meetsAtE[girl_4,boy_11,1]", "X": 1}, { "VarName": "meetsAtE[girl_4,boy_12,2]", "X": 1}, { "VarName": "meetsAtE[girl_4,boy_13,1]", "X": 1}, { "VarName": "meetsAtE[girl_4,boy_13,6]", "X": 1}, { "VarName": "meetsAtE[girl_5,girl_6,5]", "X": 1}, { "VarName": "meetsAtE[girl_5,girl_7,4]", "X": 1}, { "VarName": "meetsAtE[girl_5,girl_8,1]", "X": 1}, { "VarName": "meetsAtE[girl_5,girl_9,3]", "X": 1}, { "VarName": "meetsAtE[girl_5,girl_11,2]", "X": 1}, { "VarName": "meetsAtE[girl_5,girl_11,6]", "X": 1}, { "VarName": "meetsAtE[girl_5,girl_12,5]", "X": 1}, { "VarName": "meetsAtE[girl_5,girl_12,7]", "X": 1}, { "VarName": "meetsAtE[girl_5,boy_0,0]", "X": 1}, { "VarName": "meetsAtE[girl_5,boy_0,4]", "X": 1}, { "VarName": "meetsAtE[girl_5,boy_2,4]", "X": 1}, { "VarName": "meetsAtE[girl_5,boy_2,6]", "X": 1}, { "VarName": "meetsAtE[girl_5,boy_3,1]", "X": 1}, { "VarName": "meetsAtE[girl_5,boy_4,7]", "X": 1}, { "VarName": "meetsAtE[girl_5,boy_5,2]", "X": 1}, { "VarName": "meetsAtE[girl_5,boy_5,7]", "X": 1}, { "VarName": "meetsAtE[girl_5,boy_6,0]", "X": 1}, { "VarName": "meetsAtE[girl_5,boy_7,2]", "X": 1}, { "VarName": "meetsAtE[girl_5,boy_7,4]", "X": 1}, { "VarName": "meetsAtE[girl_5,boy_8,1]", "X": 1}, { "VarName": "meetsAtE[girl_5,boy_9,5]", "X": 1}, { "VarName": "meetsAtE[girl_5,boy_10,5]", "X": 1}, { "VarName": "meetsAtE[girl_5,boy_11,2]", "X": 1}, { "VarName": "meetsAtE[girl_5,boy_12,6]", "X": 1}, { "VarName": "meetsAtE[girl_5,boy_13,0]", "X": 1}, { "VarName": "meetsAtE[girl_6,girl_7,3]", "X": 1}, { "VarName": "meetsAtE[girl_6,girl_10,1]", "X": 1}, { "VarName": "meetsAtE[girl_6,girl_10,6]", "X": 1}, { "VarName": "meetsAtE[girl_6,girl_11,0]", "X": 1}, { "VarName": "meetsAtE[girl_6,girl_12,2]", "X": 1}, { "VarName": "meetsAtE[girl_6,girl_12,5]", "X": 1}, { "VarName": "meetsAtE[girl_6,boy_0,7]", "X": 1}, { "VarName": "meetsAtE[girl_6,boy_1,2]", "X": 1}, { "VarName": "meetsAtE[girl_6,boy_2,1]", "X": 1}, { "VarName": "meetsAtE[girl_6,boy_3,3]", "X": 1}, { "VarName": "meetsAtE[girl_6,boy_3,6]", "X": 1}, { "VarName": "meetsAtE[girl_6,boy_4,2]", "X": 1}, { "VarName": "meetsAtE[girl_6,boy_5,3]", "X": 1}, { "VarName": "meetsAtE[girl_6,boy_6,2]", "X": 1}, { "VarName": "meetsAtE[girl_6,boy_7,1]", "X": 1}, { "VarName": "meetsAtE[girl_6,boy_9,5]", "X": 1}, { "VarName": "meetsAtE[girl_6,boy_10,5]", "X": 1}, { "VarName": "meetsAtE[girl_6,boy_10,7]", "X": 1}, { "VarName": "meetsAtE[girl_6,boy_11,6]", "X": 1}, { "VarName": "meetsAtE[girl_6,boy_12,4]", "X": 1}, { "VarName": "meetsAtE[girl_6,boy_13,4]", "X": 1}, { "VarName": "meetsAtE[girl_7,girl_8,7]", "X": 1}, { "VarName": "meetsAtE[girl_7,girl_9,2]", "X": 1}, { "VarName": "meetsAtE[girl_7,girl_11,1]", "X": 1}, { "VarName": "meetsAtE[girl_7,girl_12,0]", "X": 1}, { "VarName": "meetsAtE[girl_7,boy_0,4]", "X": 1}, { "VarName": "meetsAtE[girl_7,boy_1,5]", "X": 1}, { "VarName": "meetsAtE[girl_7,boy_2,0]", "X": 1}, { "VarName": "meetsAtE[girl_7,boy_2,4]", "X": 1}, { "VarName": "meetsAtE[girl_7,boy_3,3]", "X": 1}, { "VarName": "meetsAtE[girl_7,boy_4,1]", "X": 1}, { "VarName": "meetsAtE[girl_7,boy_4,5]", "X": 1}, { "VarName": "meetsAtE[girl_7,boy_5,3]", "X": 1}, { "VarName": "meetsAtE[girl_7,boy_6,6]", "X": 1}, { "VarName": "meetsAtE[girl_7,boy_7,4]", "X": 1}, { "VarName": "meetsAtE[girl_7,boy_8,0]", "X": 1}, { "VarName": "meetsAtE[girl_7,boy_8,2]", "X": 1}, { "VarName": "meetsAtE[girl_7,boy_8,6]", "X": 1}, { "VarName": "meetsAtE[girl_7,boy_9,1]", "X": 1}, { "VarName": "meetsAtE[girl_7,boy_10,6]", "X": 1}, { "VarName": "meetsAtE[girl_7,boy_11,5]", "X": 1}, { "VarName": "meetsAtE[girl_7,boy_11,7]", "X": 1}, { "VarName": "meetsAtE[girl_7,boy_12,7]", "X": 1}, { "VarName": "meetsAtE[girl_7,boy_13,2]", "X": 1}, { "VarName": "meetsAtE[girl_8,girl_9,4]", "X": 1}, { "VarName": "meetsAtE[girl_8,girl_10,0]", "X": 1}, { "VarName": "meetsAtE[girl_8,girl_11,5]", "X": 1}, { "VarName": "meetsAtE[girl_8,girl_12,4]", "X": 1}, { "VarName": "meetsAtE[girl_8,boy_0,5]", "X": 1}, { "VarName": "meetsAtE[girl_8,boy_1,4]", "X": 1}, { "VarName": "meetsAtE[girl_8,boy_2,2]", "X": 1}, { "VarName": "meetsAtE[girl_8,boy_3,1]", "X": 1}, { "VarName": "meetsAtE[girl_8,boy_3,5]", "X": 1}, { "VarName": "meetsAtE[girl_8,boy_4,0]", "X": 1}, { "VarName": "meetsAtE[girl_8,boy_5,0]", "X": 1}, { "VarName": "meetsAtE[girl_8,boy_5,4]", "X": 1}, { "VarName": "meetsAtE[girl_8,boy_5,6]", "X": 1}, { "VarName": "meetsAtE[girl_8,boy_6,3]", "X": 1}, { "VarName": "meetsAtE[girl_8,boy_7,3]", "X": 1}, { "VarName": "meetsAtE[girl_8,boy_8,1]", "X": 1}, { "VarName": "meetsAtE[girl_8,boy_9,3]", "X": 1}, { "VarName": "meetsAtE[girl_8,boy_10,2]", "X": 1}, { "VarName": "meetsAtE[girl_8,boy_11,7]", "X": 1}, { "VarName": "meetsAtE[girl_8,boy_12,7]", "X": 1}, { "VarName": "meetsAtE[girl_8,boy_13,6]", "X": 1}, { "VarName": "meetsAtE[girl_9,girl_10,7]", "X": 1}, { "VarName": "meetsAtE[girl_9,girl_12,4]", "X": 1}, { "VarName": "meetsAtE[girl_9,boy_0,6]", "X": 1}, { "VarName": "meetsAtE[girl_9,boy_1,4]", "X": 1}, { "VarName": "meetsAtE[girl_9,boy_2,5]", "X": 1}, { "VarName": "meetsAtE[girl_9,boy_4,6]", "X": 1}, { "VarName": "meetsAtE[girl_9,boy_5,4]", "X": 1}, { "VarName": "meetsAtE[girl_9,boy_6,1]", "X": 1}, { "VarName": "meetsAtE[girl_9,boy_6,5]", "X": 1}, { "VarName": "meetsAtE[girl_9,boy_6,7]", "X": 1}, { "VarName": "meetsAtE[girl_9,boy_7,7]", "X": 1}, { "VarName": "meetsAtE[girl_9,boy_8,2]", "X": 1}, { "VarName": "meetsAtE[girl_9,boy_9,6]", "X": 1}, { "VarName": "meetsAtE[girl_9,boy_10,0]", "X": 1}, { "VarName": "meetsAtE[girl_9,boy_11,0]", "X": 1}, { "VarName": "meetsAtE[girl_9,boy_12,1]", "X": 1}, { "VarName": "meetsAtE[girl_9,boy_13,2]", "X": 1}, { "VarName": "meetsAtE[girl_10,girl_11,3]", "X": 1}, { "VarName": "meetsAtE[girl_10,girl_12,3]", "X": 1}, { "VarName": "meetsAtE[girl_10,boy_0,2]", "X": 1}, { "VarName": "meetsAtE[girl_10,boy_2,1]", "X": 1}, { "VarName": "meetsAtE[girl_10,boy_3,6]", "X": 1}, { "VarName": "meetsAtE[girl_10,boy_4,0]", "X": 1}, { "VarName": "meetsAtE[girl_10,boy_5,0]", "X": 1}, { "VarName": "meetsAtE[girl_10,boy_5,5]", "X": 1}, { "VarName": "meetsAtE[girl_10,boy_6,7]", "X": 1}, { "VarName": "meetsAtE[girl_10,boy_7,1]", "X": 1}, { "VarName": "meetsAtE[girl_10,boy_7,7]", "X": 1}, { "VarName": "meetsAtE[girl_10,boy_8,5]", "X": 1}, { "VarName": "meetsAtE[girl_10,boy_9,4]", "X": 1}, { "VarName": "meetsAtE[girl_10,boy_10,3]", "X": 1}, { "VarName": "meetsAtE[girl_10,boy_11,4]", "X": 1}, { "VarName": "meetsAtE[girl_10,boy_11,6]", "X": 1}, { "VarName": "meetsAtE[girl_10,boy_12,2]", "X": 1}, { "VarName": "meetsAtE[girl_10,boy_12,5]", "X": 1}, { "VarName": "meetsAtE[girl_10,boy_13,3]", "X": 1}, { "VarName": "meetsAtE[girl_11,girl_12,3]", "X": 1}, { "VarName": "meetsAtE[girl_11,boy_0,5]", "X": 1}, { "VarName": "meetsAtE[girl_11,boy_1,7]", "X": 1}, { "VarName": "meetsAtE[girl_11,boy_2,6]", "X": 1}, { "VarName": "meetsAtE[girl_11,boy_3,5]", "X": 1}, { "VarName": "meetsAtE[girl_11,boy_4,1]", "X": 1}, { "VarName": "meetsAtE[girl_11,boy_5,2]", "X": 1}, { "VarName": "meetsAtE[girl_11,boy_6,4]", "X": 1}, { "VarName": "meetsAtE[girl_11,boy_7,2]", "X": 1}, { "VarName": "meetsAtE[girl_11,boy_8,4]", "X": 1}, { "VarName": "meetsAtE[girl_11,boy_8,7]", "X": 1}, { "VarName": "meetsAtE[girl_11,boy_9,1]", "X": 1}, { "VarName": "meetsAtE[girl_11,boy_10,3]", "X": 1}, { "VarName": "meetsAtE[girl_11,boy_11,2]", "X": 1}, { "VarName": "meetsAtE[girl_11,boy_12,6]", "X": 1}, { "VarName": "meetsAtE[girl_11,boy_13,3]", "X": 1}, { "VarName": "meetsAtE[girl_12,boy_1,2]", "X": 1}, { "VarName": "meetsAtE[girl_12,boy_1,4]", "X": 1}, { "VarName": "meetsAtE[girl_12,boy_1,6]", "X": 1}, { "VarName": "meetsAtE[girl_12,boy_2,0]", "X": 1}, { "VarName": "meetsAtE[girl_12,boy_4,2]", "X": 1}, { "VarName": "meetsAtE[girl_12,boy_4,7]", "X": 1}, { "VarName": "meetsAtE[girl_12,boy_5,4]", "X": 1}, { "VarName": "meetsAtE[girl_12,boy_5,7]", "X": 1}, { "VarName": "meetsAtE[girl_12,boy_6,2]", "X": 1}, { "VarName": "meetsAtE[girl_12,boy_7,6]", "X": 1}, { "VarName": "meetsAtE[girl_12,boy_8,0]", "X": 1}, { "VarName": "meetsAtE[girl_12,boy_9,5]", "X": 1}, { "VarName": "meetsAtE[girl_12,boy_10,3]", "X": 1}, { "VarName": "meetsAtE[girl_12,boy_10,5]", "X": 1}, { "VarName": "meetsAtE[girl_12,boy_11,1]", "X": 1}, { "VarName": "meetsAtE[girl_12,boy_13,1]", "X": 1}, { "VarName": "meetsAtE[girl_12,boy_13,3]", "X": 1}, { "VarName": "meetsAtE[boy_0,boy_1,1]", "X": 1}, { "VarName": "meetsAtE[boy_0,boy_1,3]", "X": 1}, { "VarName": "meetsAtE[boy_0,boy_2,4]", "X": 1}, { "VarName": "meetsAtE[boy_0,boy_3,5]", "X": 1}, { "VarName": "meetsAtE[boy_0,boy_4,6]", "X": 1}, { "VarName": "meetsAtE[boy_0,boy_5,1]", "X": 1}, { "VarName": "meetsAtE[boy_0,boy_6,0]", "X": 1}, { "VarName": "meetsAtE[boy_0,boy_7,4]", "X": 1}, { "VarName": "meetsAtE[boy_0,boy_8,3]", "X": 1}, { "VarName": "meetsAtE[boy_0,boy_9,6]", "X": 1}, { "VarName": "meetsAtE[boy_0,boy_10,1]", "X": 1}, { "VarName": "meetsAtE[boy_0,boy_10,7]", "X": 1}, { "VarName": "meetsAtE[boy_0,boy_12,2]", "X": 1}, { "VarName": "meetsAtE[boy_0,boy_13,0]", "X": 1}, { "VarName": "meetsAtE[boy_1,boy_3,0]", "X": 1}, { "VarName": "meetsAtE[boy_1,boy_4,2]", "X": 1}, { "VarName": "meetsAtE[boy_1,boy_4,5]", "X": 1}, { "VarName": "meetsAtE[boy_1,boy_5,1]", "X": 1}, { "VarName": "meetsAtE[boy_1,boy_5,4]", "X": 1}, { "VarName": "meetsAtE[boy_1,boy_6,2]", "X": 1}, { "VarName": "meetsAtE[boy_1,boy_7,0]", "X": 1}, { "VarName": "meetsAtE[boy_1,boy_7,6]", "X": 1}, { "VarName": "meetsAtE[boy_1,boy_8,3]", "X": 1}, { "VarName": "meetsAtE[boy_1,boy_8,7]", "X": 1}, { "VarName": "meetsAtE[boy_1,boy_9,0]", "X": 1}, { "VarName": "meetsAtE[boy_1,boy_10,1]", "X": 1}, { "VarName": "meetsAtE[boy_1,boy_11,5]", "X": 1}, { "VarName": "meetsAtE[boy_1,boy_12,0]", "X": 1}, { "VarName": "meetsAtE[boy_2,boy_3,7]", "X": 1}, { "VarName": "meetsAtE[boy_2,boy_4,3]", "X": 1}, { "VarName": "meetsAtE[boy_2,boy_6,5]", "X": 1}, { "VarName": "meetsAtE[boy_2,boy_7,1]", "X": 1}, { "VarName": "meetsAtE[boy_2,boy_7,4]", "X": 1}, { "VarName": "meetsAtE[boy_2,boy_8,0]", "X": 1}, { "VarName": "meetsAtE[boy_2,boy_9,7]", "X": 1}, { "VarName": "meetsAtE[boy_2,boy_10,2]", "X": 1}, { "VarName": "meetsAtE[boy_2,boy_11,3]", "X": 1}, { "VarName": "meetsAtE[boy_2,boy_12,3]", "X": 1}, { "VarName": "meetsAtE[boy_2,boy_12,6]", "X": 1}, { "VarName": "meetsAtE[boy_2,boy_13,7]", "X": 1}, { "VarName": "meetsAtE[boy_3,boy_4,4]", "X": 1}, { "VarName": "meetsAtE[boy_3,boy_5,3]", "X": 1}, { "VarName": "meetsAtE[boy_3,boy_7,0]", "X": 1}, { "VarName": "meetsAtE[boy_3,boy_8,1]", "X": 1}, { "VarName": "meetsAtE[boy_3,boy_9,0]", "X": 1}, { "VarName": "meetsAtE[boy_3,boy_9,2]", "X": 1}, { "VarName": "meetsAtE[boy_3,boy_9,7]", "X": 1}, { "VarName": "meetsAtE[boy_3,boy_10,4]", "X": 1}, { "VarName": "meetsAtE[boy_3,boy_11,6]", "X": 1}, { "VarName": "meetsAtE[boy_3,boy_12,0]", "X": 1}, { "VarName": "meetsAtE[boy_3,boy_13,7]", "X": 1}, { "VarName": "meetsAtE[boy_4,boy_5,0]", "X": 1}, { "VarName": "meetsAtE[boy_4,boy_5,7]", "X": 1}, { "VarName": "meetsAtE[boy_4,boy_6,2]", "X": 1}, { "VarName": "meetsAtE[boy_4,boy_9,1]", "X": 1}, { "VarName": "meetsAtE[boy_4,boy_9,6]", "X": 1}, { "VarName": "meetsAtE[boy_4,boy_10,4]", "X": 1}, { "VarName": "meetsAtE[boy_4,boy_11,3]", "X": 1}, { "VarName": "meetsAtE[boy_4,boy_11,5]", "X": 1}, { "VarName": "meetsAtE[boy_4,boy_12,3]", "X": 1}, { "VarName": "meetsAtE[boy_5,boy_7,2]", "X": 1}, { "VarName": "meetsAtE[boy_5,boy_8,5]", "X": 1}, { "VarName": "meetsAtE[boy_5,boy_10,1]", "X": 1}, { "VarName": "meetsAtE[boy_5,boy_11,2]", "X": 1}, { "VarName": "meetsAtE[boy_5,boy_12,5]", "X": 1}, { "VarName": "meetsAtE[boy_5,boy_13,6]", "X": 1}, { "VarName": "meetsAtE[boy_6,boy_7,3]", "X": 1}, { "VarName": "meetsAtE[boy_6,boy_7,7]", "X": 1}, { "VarName": "meetsAtE[boy_6,boy_8,4]", "X": 1}, { "VarName": "meetsAtE[boy_6,boy_8,6]", "X": 1}, { "VarName": "meetsAtE[boy_6,boy_9,3]", "X": 1}, { "VarName": "meetsAtE[boy_6,boy_10,6]", "X": 1}, { "VarName": "meetsAtE[boy_6,boy_12,1]", "X": 1}, { "VarName": "meetsAtE[boy_6,boy_13,0]", "X": 1}, { "VarName": "meetsAtE[boy_7,boy_9,0]", "X": 1}, { "VarName": "meetsAtE[boy_7,boy_9,3]", "X": 1}, { "VarName": "meetsAtE[boy_7,boy_11,2]", "X": 1}, { "VarName": "meetsAtE[boy_7,boy_12,0]", "X": 1}, { "VarName": "meetsAtE[boy_7,boy_13,5]", "X": 1}, { "VarName": "meetsAtE[boy_8,boy_10,6]", "X": 1}, { "VarName": "meetsAtE[boy_8,boy_12,5]", "X": 1}, { "VarName": "meetsAtE[boy_8,boy_13,2]", "X": 1}, { "VarName": "meetsAtE[boy_9,boy_10,5]", "X": 1}, { "VarName": "meetsAtE[boy_9,boy_11,4]", "X": 1}, { "VarName": "meetsAtE[boy_9,boy_12,0]", "X": 1}, { "VarName": "meetsAtE[boy_9,boy_13,7]", "X": 1}, { "VarName": "meetsAtE[boy_10,boy_11,0]", "X": 1}, { "VarName": "meetsAtE[boy_10,boy_13,3]", "X": 1}, { "VarName": "meetsAtE[boy_11,boy_12,3]", "X": 1}, { "VarName": "meetsAtE[boy_11,boy_12,7]", "X": 1}, { "VarName": "meetsAtE[boy_11,boy_13,1]", "X": 1}, { "VarName": "meetsAtE[boy_12,boy_13,4]", "X": 1}, { "VarName": "meetsAtEInG[girl_0,girl_1,4,2]", "X": 1}, { "VarName": "meetsAtEInG[girl_0,girl_2,0,7]", "X": 1}, { "VarName": "meetsAtEInG[girl_0,girl_3,2,3]", "X": 1}, { "VarName": "meetsAtEInG[girl_0,girl_4,1,4]", "X": 1}, { "VarName": "meetsAtEInG[girl_0,girl_5,2,0]", "X": 1}, { "VarName": "meetsAtEInG[girl_0,girl_5,2,3]", "X": 1}, { "VarName": "meetsAtEInG[girl_0,girl_6,0,7]", "X": 1}, { "VarName": "meetsAtEInG[girl_0,girl_7,5,1]", "X": 1}, { "VarName": "meetsAtEInG[girl_0,girl_8,4,2]", "X": 1}, { "VarName": "meetsAtEInG[girl_0,girl_9,2,3]", "X": 1}, { "VarName": "meetsAtEInG[girl_0,girl_10,2,5]", "X": 1}, { "VarName": "meetsAtEInG[girl_0,girl_11,5,1]", "X": 1}, { "VarName": "meetsAtEInG[girl_0,girl_12,3,6]", "X": 1}, { "VarName": "meetsAtEInG[girl_0,boy_0,0,7]", "X": 1}, { "VarName": "meetsAtEInG[girl_0,boy_0,2,0]", "X": 1}, { "VarName": "meetsAtEInG[girl_0,boy_1,3,6]", "X": 1}, { "VarName": "meetsAtEInG[girl_0,boy_2,4,2]", "X": 1}, { "VarName": "meetsAtEInG[girl_0,boy_3,1,4]", "X": 1}, { "VarName": "meetsAtEInG[girl_0,boy_4,1,4]", "X": 1}, { "VarName": "meetsAtEInG[girl_0,boy_4,5,1]", "X": 1}, { "VarName": "meetsAtEInG[girl_0,boy_5,2,5]", "X": 1}, { "VarName": "meetsAtEInG[girl_0,boy_6,2,0]", "X": 1}, { "VarName": "meetsAtEInG[girl_0,boy_7,3,6]", "X": 1}, { "VarName": "meetsAtEInG[girl_0,boy_8,2,5]", "X": 1}, { "VarName": "meetsAtEInG[girl_0,boy_9,5,1]", "X": 1}, { "VarName": "meetsAtEInG[girl_0,boy_10,0,7]", "X": 1}, { "VarName": "meetsAtEInG[girl_0,boy_10,1,4]", "X": 1}, { "VarName": "meetsAtEInG[girl_0,boy_10,4,2]", "X": 1}, { "VarName": "meetsAtEInG[girl_0,boy_12,2,5]", "X": 1}, { "VarName": "meetsAtEInG[girl_0,boy_13,2,0]", "X": 1}, { "VarName": "meetsAtEInG[girl_1,girl_2,1,3]", "X": 1}, { "VarName": "meetsAtEInG[girl_1,girl_3,1,5]", "X": 1}, { "VarName": "meetsAtEInG[girl_1,girl_4,4,0]", "X": 1}, { "VarName": "meetsAtEInG[girl_1,girl_5,2,7]", "X": 1}, { "VarName": "meetsAtEInG[girl_1,girl_6,4,0]", "X": 1}, { "VarName": "meetsAtEInG[girl_1,girl_7,5,6]", "X": 1}, { "VarName": "meetsAtEInG[girl_1,girl_8,4,2]", "X": 1}, { "VarName": "meetsAtEInG[girl_1,girl_9,0,1]", "X": 1}, { "VarName": "meetsAtEInG[girl_1,girl_10,5,4]", "X": 1}, { "VarName": "meetsAtEInG[girl_1,girl_11,4,0]", "X": 1}, { "VarName": "meetsAtEInG[girl_1,girl_12,2,7]", "X": 1}, { "VarName": "meetsAtEInG[girl_1,boy_0,1,3]", "X": 1}, { "VarName": "meetsAtEInG[girl_1,boy_1,1,3]", "X": 1}, { "VarName": "meetsAtEInG[girl_1,boy_2,4,2]", "X": 1}, { "VarName": "meetsAtEInG[girl_1,boy_4,2,7]", "X": 1}, { "VarName": "meetsAtEInG[girl_1,boy_5,2,7]", "X": 1}, { "VarName": "meetsAtEInG[girl_1,boy_6,0,1]", "X": 1}, { "VarName": "meetsAtEInG[girl_1,boy_6,5,6]", "X": 1}, { "VarName": "meetsAtEInG[girl_1,boy_7,1,5]", "X": 1}, { "VarName": "meetsAtEInG[girl_1,boy_8,1,3]", "X": 1}, { "VarName": "meetsAtEInG[girl_1,boy_8,5,6]", "X": 1}, { "VarName": "meetsAtEInG[girl_1,boy_9,5,4]", "X": 1}, { "VarName": "meetsAtEInG[girl_1,boy_10,4,2]", "X": 1}, { "VarName": "meetsAtEInG[girl_1,boy_10,5,6]", "X": 1}, { "VarName": "meetsAtEInG[girl_1,boy_11,5,4]", "X": 1}, { "VarName": "meetsAtEInG[girl_1,boy_12,0,1]", "X": 1}, { "VarName": "meetsAtEInG[girl_1,boy_13,1,5]", "X": 1}, { "VarName": "meetsAtEInG[girl_2,girl_3,0,2]", "X": 1}, { "VarName": "meetsAtEInG[girl_2,girl_4,3,1]", "X": 1}, { "VarName": "meetsAtEInG[girl_2,girl_5,2,6]", "X": 1}, { "VarName": "meetsAtEInG[girl_2,girl_6,0,7]", "X": 1}, { "VarName": "meetsAtEInG[girl_2,girl_6,4,4]", "X": 1}, { "VarName": "meetsAtEInG[girl_2,girl_7,5,5]", "X": 1}, { "VarName": "meetsAtEInG[girl_2,girl_8,1,0]", "X": 1}, { "VarName": "meetsAtEInG[girl_2,girl_10,1,0]", "X": 1}, { "VarName": "meetsAtEInG[girl_2,girl_11,2,6]", "X": 1}, { "VarName": "meetsAtEInG[girl_2,girl_12,3,1]", "X": 1}, { "VarName": "meetsAtEInG[girl_2,boy_0,0,7]", "X": 1}, { "VarName": "meetsAtEInG[girl_2,boy_0,1,3]", "X": 1}, { "VarName": "meetsAtEInG[girl_2,boy_1,1,3]", "X": 1}, { "VarName": "meetsAtEInG[girl_2,boy_1,5,5]", "X": 1}, { "VarName": "meetsAtEInG[girl_2,boy_2,2,6]", "X": 1}, { "VarName": "meetsAtEInG[girl_2,boy_3,0,2]", "X": 1}, { "VarName": "meetsAtEInG[girl_2,boy_4,1,0]", "X": 1}, { "VarName": "meetsAtEInG[girl_2,boy_4,5,5]", "X": 1}, { "VarName": "meetsAtEInG[girl_2,boy_5,1,0]", "X": 1}, { "VarName": "meetsAtEInG[girl_2,boy_8,1,3]", "X": 1}, { "VarName": "meetsAtEInG[girl_2,boy_9,0,2]", "X": 1}, { "VarName": "meetsAtEInG[girl_2,boy_10,0,7]", "X": 1}, { "VarName": "meetsAtEInG[girl_2,boy_11,3,1]", "X": 1}, { "VarName": "meetsAtEInG[girl_2,boy_11,5,5]", "X": 1}, { "VarName": "meetsAtEInG[girl_2,boy_12,2,6]", "X": 1}, { "VarName": "meetsAtEInG[girl_2,boy_12,4,4]", "X": 1}, { "VarName": "meetsAtEInG[girl_2,boy_13,3,1]", "X": 1}, { "VarName": "meetsAtEInG[girl_2,boy_13,4,4]", "X": 1}, { "VarName": "meetsAtEInG[girl_3,girl_5,2,3]", "X": 1}, { "VarName": "meetsAtEInG[girl_3,girl_6,2,1]", "X": 1}, { "VarName": "meetsAtEInG[girl_3,girl_7,5,7]", "X": 1}, { "VarName": "meetsAtEInG[girl_3,girl_8,5,7]", "X": 1}, { "VarName": "meetsAtEInG[girl_3,girl_9,0,0]", "X": 1}, { "VarName": "meetsAtEInG[girl_3,girl_9,0,6]", "X": 1}, { "VarName": "meetsAtEInG[girl_3,girl_9,2,3]", "X": 1}, { "VarName": "meetsAtEInG[girl_3,girl_10,2,1]", "X": 1}, { "VarName": "meetsAtEInG[girl_3,girl_11,3,4]", "X": 1}, { "VarName": "meetsAtEInG[girl_3,boy_0,0,6]", "X": 1}, { "VarName": "meetsAtEInG[girl_3,boy_2,2,1]", "X": 1}, { "VarName": "meetsAtEInG[girl_3,boy_3,0,2]", "X": 1}, { "VarName": "meetsAtEInG[girl_3,boy_4,0,6]", "X": 1}, { "VarName": "meetsAtEInG[girl_3,boy_6,3,4]", "X": 1}, { "VarName": "meetsAtEInG[girl_3,boy_7,1,5]", "X": 1}, { "VarName": "meetsAtEInG[girl_3,boy_7,2,1]", "X": 1}, { "VarName": "meetsAtEInG[girl_3,boy_8,3,4]", "X": 1}, { "VarName": "meetsAtEInG[girl_3,boy_9,0,2]", "X": 1}, { "VarName": "meetsAtEInG[girl_3,boy_9,0,6]", "X": 1}, { "VarName": "meetsAtEInG[girl_3,boy_10,0,0]", "X": 1}, { "VarName": "meetsAtEInG[girl_3,boy_11,0,0]", "X": 1}, { "VarName": "meetsAtEInG[girl_3,boy_11,5,7]", "X": 1}, { "VarName": "meetsAtEInG[girl_3,boy_12,5,7]", "X": 1}, { "VarName": "meetsAtEInG[girl_3,boy_13,1,5]", "X": 1}, { "VarName": "meetsAtEInG[girl_4,girl_6,4,0]", "X": 1}, { "VarName": "meetsAtEInG[girl_4,girl_8,4,3]", "X": 1}, { "VarName": "meetsAtEInG[girl_4,girl_8,4,6]", "X": 1}, { "VarName": "meetsAtEInG[girl_4,girl_9,0,5]", "X": 1}, { "VarName": "meetsAtEInG[girl_4,girl_10,1,2]", "X": 1}, { "VarName": "meetsAtEInG[girl_4,girl_11,3,7]", "X": 1}, { "VarName": "meetsAtEInG[girl_4,girl_11,4,0]", "X": 1}, { "VarName": "meetsAtEInG[girl_4,girl_12,3,1]", "X": 1}, { "VarName": "meetsAtEInG[girl_4,boy_0,1,2]", "X": 1}, { "VarName": "meetsAtEInG[girl_4,boy_1,3,7]", "X": 1}, { "VarName": "meetsAtEInG[girl_4,boy_2,0,5]", "X": 1}, { "VarName": "meetsAtEInG[girl_4,boy_3,1,4]", "X": 1}, { "VarName": "meetsAtEInG[girl_4,boy_4,1,4]", "X": 1}, { "VarName": "meetsAtEInG[girl_4,boy_5,4,6]", "X": 1}, { "VarName": "meetsAtEInG[girl_4,boy_6,0,5]", "X": 1}, { "VarName": "meetsAtEInG[girl_4,boy_6,4,3]", "X": 1}, { "VarName": "meetsAtEInG[girl_4,boy_7,4,3]", "X": 1}, { "VarName": "meetsAtEInG[girl_4,boy_8,3,7]", "X": 1}, { "VarName": "meetsAtEInG[girl_4,boy_9,4,3]", "X": 1}, { "VarName": "meetsAtEInG[girl_4,boy_10,1,4]", "X": 1}, { "VarName": "meetsAtEInG[girl_4,boy_11,3,1]", "X": 1}, { "VarName": "meetsAtEInG[girl_4,boy_12,1,2]", "X": 1}, { "VarName": "meetsAtEInG[girl_4,boy_13,3,1]", "X": 1}, { "VarName": "meetsAtEInG[girl_4,boy_13,4,6]", "X": 1}, { "VarName": "meetsAtEInG[girl_5,girl_6,4,5]", "X": 1}, { "VarName": "meetsAtEInG[girl_5,girl_7,2,4]", "X": 1}, { "VarName": "meetsAtEInG[girl_5,girl_8,4,1]", "X": 1}, { "VarName": "meetsAtEInG[girl_5,girl_9,2,3]", "X": 1}, { "VarName": "meetsAtEInG[girl_5,girl_11,2,2]", "X": 1}, { "VarName": "meetsAtEInG[girl_5,girl_11,2,6]", "X": 1}, { "VarName": "meetsAtEInG[girl_5,girl_12,2,7]", "X": 1}, { "VarName": "meetsAtEInG[girl_5,girl_12,4,5]", "X": 1}, { "VarName": "meetsAtEInG[girl_5,boy_0,2,0]", "X": 1}, { "VarName": "meetsAtEInG[girl_5,boy_0,2,4]", "X": 1}, { "VarName": "meetsAtEInG[girl_5,boy_2,2,4]", "X": 1}, { "VarName": "meetsAtEInG[girl_5,boy_2,2,6]", "X": 1}, { "VarName": "meetsAtEInG[girl_5,boy_3,4,1]", "X": 1}, { "VarName": "meetsAtEInG[girl_5,boy_4,2,7]", "X": 1}, { "VarName": "meetsAtEInG[girl_5,boy_5,2,2]", "X": 1}, { "VarName": "meetsAtEInG[girl_5,boy_5,2,7]", "X": 1}, { "VarName": "meetsAtEInG[girl_5,boy_6,2,0]", "X": 1}, { "VarName": "meetsAtEInG[girl_5,boy_7,2,2]", "X": 1}, { "VarName": "meetsAtEInG[girl_5,boy_7,2,4]", "X": 1}, { "VarName": "meetsAtEInG[girl_5,boy_8,4,1]", "X": 1}, { "VarName": "meetsAtEInG[girl_5,boy_9,4,5]", "X": 1}, { "VarName": "meetsAtEInG[girl_5,boy_10,4,5]", "X": 1}, { "VarName": "meetsAtEInG[girl_5,boy_11,2,2]", "X": 1}, { "VarName": "meetsAtEInG[girl_5,boy_12,2,6]", "X": 1}, { "VarName": "meetsAtEInG[girl_5,boy_13,2,0]", "X": 1}, { "VarName": "meetsAtEInG[girl_6,girl_7,5,3]", "X": 1}, { "VarName": "meetsAtEInG[girl_6,girl_10,1,6]", "X": 1}, { "VarName": "meetsAtEInG[girl_6,girl_10,2,1]", "X": 1}, { "VarName": "meetsAtEInG[girl_6,girl_11,4,0]", "X": 1}, { "VarName": "meetsAtEInG[girl_6,girl_12,3,2]", "X": 1}, { "VarName": "meetsAtEInG[girl_6,girl_12,4,5]", "X": 1}, { "VarName": "meetsAtEInG[girl_6,boy_0,0,7]", "X": 1}, { "VarName": "meetsAtEInG[girl_6,boy_1,3,2]", "X": 1}, { "VarName": "meetsAtEInG[girl_6,boy_2,2,1]", "X": 1}, { "VarName": "meetsAtEInG[girl_6,boy_3,1,6]", "X": 1}, { "VarName": "meetsAtEInG[girl_6,boy_3,5,3]", "X": 1}, { "VarName": "meetsAtEInG[girl_6,boy_4,3,2]", "X": 1}, { "VarName": "meetsAtEInG[girl_6,boy_5,5,3]", "X": 1}, { "VarName": "meetsAtEInG[girl_6,boy_6,3,2]", "X": 1}, { "VarName": "meetsAtEInG[girl_6,boy_7,2,1]", "X": 1}, { "VarName": "meetsAtEInG[girl_6,boy_9,4,5]", "X": 1}, { "VarName": "meetsAtEInG[girl_6,boy_10,0,7]", "X": 1}, { "VarName": "meetsAtEInG[girl_6,boy_10,4,5]", "X": 1}, { "VarName": "meetsAtEInG[girl_6,boy_11,1,6]", "X": 1}, { "VarName": "meetsAtEInG[girl_6,boy_12,4,4]", "X": 1}, { "VarName": "meetsAtEInG[girl_6,boy_13,4,4]", "X": 1}, { "VarName": "meetsAtEInG[girl_7,girl_8,5,7]", "X": 1}, { "VarName": "meetsAtEInG[girl_7,girl_9,5,2]", "X": 1}, { "VarName": "meetsAtEInG[girl_7,girl_11,5,1]", "X": 1}, { "VarName": "meetsAtEInG[girl_7,girl_12,3,0]", "X": 1}, { "VarName": "meetsAtEInG[girl_7,boy_0,2,4]", "X": 1}, { "VarName": "meetsAtEInG[girl_7,boy_1,5,5]", "X": 1}, { "VarName": "meetsAtEInG[girl_7,boy_2,2,4]", "X": 1}, { "VarName": "meetsAtEInG[girl_7,boy_2,3,0]", "X": 1}, { "VarName": "meetsAtEInG[girl_7,boy_3,5,3]", "X": 1}, { "VarName": "meetsAtEInG[girl_7,boy_4,5,1]", "X": 1}, { "VarName": "meetsAtEInG[girl_7,boy_4,5,5]", "X": 1}, { "VarName": "meetsAtEInG[girl_7,boy_5,5,3]", "X": 1}, { "VarName": "meetsAtEInG[girl_7,boy_6,5,6]", "X": 1}, { "VarName": "meetsAtEInG[girl_7,boy_7,2,4]", "X": 1}, { "VarName": "meetsAtEInG[girl_7,boy_8,3,0]", "X": 1}, { "VarName": "meetsAtEInG[girl_7,boy_8,5,2]", "X": 1}, { "VarName": "meetsAtEInG[girl_7,boy_8,5,6]", "X": 1}, { "VarName": "meetsAtEInG[girl_7,boy_9,5,1]", "X": 1}, { "VarName": "meetsAtEInG[girl_7,boy_10,5,6]", "X": 1}, { "VarName": "meetsAtEInG[girl_7,boy_11,5,5]", "X": 1}, { "VarName": "meetsAtEInG[girl_7,boy_11,5,7]", "X": 1}, { "VarName": "meetsAtEInG[girl_7,boy_12,5,7]", "X": 1}, { "VarName": "meetsAtEInG[girl_7,boy_13,5,2]", "X": 1}, { "VarName": "meetsAtEInG[girl_8,girl_9,0,4]", "X": 1}, { "VarName": "meetsAtEInG[girl_8,girl_10,1,0]", "X": 1}, { "VarName": "meetsAtEInG[girl_8,girl_11,3,5]", "X": 1}, { "VarName": "meetsAtEInG[girl_8,girl_12,0,4]", "X": 1}, { "VarName": "meetsAtEInG[girl_8,boy_0,3,5]", "X": 1}, { "VarName": "meetsAtEInG[girl_8,boy_1,0,4]", "X": 1}, { "VarName": "meetsAtEInG[girl_8,boy_2,4,2]", "X": 1}, { "VarName": "meetsAtEInG[girl_8,boy_3,3,5]", "X": 1}, { "VarName": "meetsAtEInG[girl_8,boy_3,4,1]", "X": 1}, { "VarName": "meetsAtEInG[girl_8,boy_4,1,0]", "X": 1}, { "VarName": "meetsAtEInG[girl_8,boy_5,0,4]", "X": 1}, { "VarName": "meetsAtEInG[girl_8,boy_5,1,0]", "X": 1}, { "VarName": "meetsAtEInG[girl_8,boy_5,4,6]", "X": 1}, { "VarName": "meetsAtEInG[girl_8,boy_6,4,3]", "X": 1}, { "VarName": "meetsAtEInG[girl_8,boy_7,4,3]", "X": 1}, { "VarName": "meetsAtEInG[girl_8,boy_8,4,1]", "X": 1}, { "VarName": "meetsAtEInG[girl_8,boy_9,4,3]", "X": 1}, { "VarName": "meetsAtEInG[girl_8,boy_10,4,2]", "X": 1}, { "VarName": "meetsAtEInG[girl_8,boy_11,5,7]", "X": 1}, { "VarName": "meetsAtEInG[girl_8,boy_12,5,7]", "X": 1}, { "VarName": "meetsAtEInG[girl_8,boy_13,4,6]", "X": 1}, { "VarName": "meetsAtEInG[girl_9,girl_10,4,7]", "X": 1}, { "VarName": "meetsAtEInG[girl_9,girl_12,0,4]", "X": 1}, { "VarName": "meetsAtEInG[girl_9,boy_0,0,6]", "X": 1}, { "VarName": "meetsAtEInG[girl_9,boy_1,0,4]", "X": 1}, { "VarName": "meetsAtEInG[girl_9,boy_2,0,5]", "X": 1}, { "VarName": "meetsAtEInG[girl_9,boy_4,0,6]", "X": 1}, { "VarName": "meetsAtEInG[girl_9,boy_5,0,4]", "X": 1}, { "VarName": "meetsAtEInG[girl_9,boy_6,0,1]", "X": 1}, { "VarName": "meetsAtEInG[girl_9,boy_6,0,5]", "X": 1}, { "VarName": "meetsAtEInG[girl_9,boy_6,4,7]", "X": 1}, { "VarName": "meetsAtEInG[girl_9,boy_7,4,7]", "X": 1}, { "VarName": "meetsAtEInG[girl_9,boy_8,5,2]", "X": 1}, { "VarName": "meetsAtEInG[girl_9,boy_9,0,6]", "X": 1}, { "VarName": "meetsAtEInG[girl_9,boy_10,0,0]", "X": 1}, { "VarName": "meetsAtEInG[girl_9,boy_11,0,0]", "X": 1}, { "VarName": "meetsAtEInG[girl_9,boy_12,0,1]", "X": 1}, { "VarName": "meetsAtEInG[girl_9,boy_13,5,2]", "X": 1}, { "VarName": "meetsAtEInG[girl_10,girl_11,3,3]", "X": 1}, { "VarName": "meetsAtEInG[girl_10,girl_12,3,3]", "X": 1}, { "VarName": "meetsAtEInG[girl_10,boy_0,1,2]", "X": 1}, { "VarName": "meetsAtEInG[girl_10,boy_2,2,1]", "X": 1}, { "VarName": "meetsAtEInG[girl_10,boy_3,1,6]", "X": 1}, { "VarName": "meetsAtEInG[girl_10,boy_4,1,0]", "X": 1}, { "VarName": "meetsAtEInG[girl_10,boy_5,1,0]", "X": 1}, { "VarName": "meetsAtEInG[girl_10,boy_5,2,5]", "X": 1}, { "VarName": "meetsAtEInG[girl_10,boy_6,4,7]", "X": 1}, { "VarName": "meetsAtEInG[girl_10,boy_7,2,1]", "X": 1}, { "VarName": "meetsAtEInG[girl_10,boy_7,4,7]", "X": 1}, { "VarName": "meetsAtEInG[girl_10,boy_8,2,5]", "X": 1}, { "VarName": "meetsAtEInG[girl_10,boy_9,5,4]", "X": 1}, { "VarName": "meetsAtEInG[girl_10,boy_10,3,3]", "X": 1}, { "VarName": "meetsAtEInG[girl_10,boy_11,1,6]", "X": 1}, { "VarName": "meetsAtEInG[girl_10,boy_11,5,4]", "X": 1}, { "VarName": "meetsAtEInG[girl_10,boy_12,1,2]", "X": 1}, { "VarName": "meetsAtEInG[girl_10,boy_12,2,5]", "X": 1}, { "VarName": "meetsAtEInG[girl_10,boy_13,3,3]", "X": 1}, { "VarName": "meetsAtEInG[girl_11,girl_12,3,3]", "X": 1}, { "VarName": "meetsAtEInG[girl_11,boy_0,3,5]", "X": 1}, { "VarName": "meetsAtEInG[girl_11,boy_1,3,7]", "X": 1}, { "VarName": "meetsAtEInG[girl_11,boy_2,2,6]", "X": 1}, { "VarName": "meetsAtEInG[girl_11,boy_3,3,5]", "X": 1}, { "VarName": "meetsAtEInG[girl_11,boy_4,5,1]", "X": 1}, { "VarName": "meetsAtEInG[girl_11,boy_5,2,2]", "X": 1}, { "VarName": "meetsAtEInG[girl_11,boy_6,3,4]", "X": 1}, { "VarName": "meetsAtEInG[girl_11,boy_7,2,2]", "X": 1}, { "VarName": "meetsAtEInG[girl_11,boy_8,3,4]", "X": 1}, { "VarName": "meetsAtEInG[girl_11,boy_8,3,7]", "X": 1}, { "VarName": "meetsAtEInG[girl_11,boy_9,5,1]", "X": 1}, { "VarName": "meetsAtEInG[girl_11,boy_10,3,3]", "X": 1}, { "VarName": "meetsAtEInG[girl_11,boy_11,2,2]", "X": 1}, { "VarName": "meetsAtEInG[girl_11,boy_12,2,6]", "X": 1}, { "VarName": "meetsAtEInG[girl_11,boy_13,3,3]", "X": 1}, { "VarName": "meetsAtEInG[girl_12,boy_1,0,4]", "X": 1}, { "VarName": "meetsAtEInG[girl_12,boy_1,3,2]", "X": 1}, { "VarName": "meetsAtEInG[girl_12,boy_1,3,6]", "X": 1}, { "VarName": "meetsAtEInG[girl_12,boy_2,3,0]", "X": 1}, { "VarName": "meetsAtEInG[girl_12,boy_4,2,7]", "X": 1}, { "VarName": "meetsAtEInG[girl_12,boy_4,3,2]", "X": 1}, { "VarName": "meetsAtEInG[girl_12,boy_5,0,4]", "X": 1}, { "VarName": "meetsAtEInG[girl_12,boy_5,2,7]", "X": 1}, { "VarName": "meetsAtEInG[girl_12,boy_6,3,2]", "X": 1}, { "VarName": "meetsAtEInG[girl_12,boy_7,3,6]", "X": 1}, { "VarName": "meetsAtEInG[girl_12,boy_8,3,0]", "X": 1}, { "VarName": "meetsAtEInG[girl_12,boy_9,4,5]", "X": 1}, { "VarName": "meetsAtEInG[girl_12,boy_10,3,3]", "X": 1}, { "VarName": "meetsAtEInG[girl_12,boy_10,4,5]", "X": 1}, { "VarName": "meetsAtEInG[girl_12,boy_11,3,1]", "X": 1}, { "VarName": "meetsAtEInG[girl_12,boy_13,3,1]", "X": 1}, { "VarName": "meetsAtEInG[girl_12,boy_13,3,3]", "X": 1}, { "VarName": "meetsAtEInG[boy_0,boy_1,1,1]", "X": 1}, { "VarName": "meetsAtEInG[boy_0,boy_1,1,3]", "X": 1}, { "VarName": "meetsAtEInG[boy_0,boy_2,2,4]", "X": 1}, { "VarName": "meetsAtEInG[boy_0,boy_3,3,5]", "X": 1}, { "VarName": "meetsAtEInG[boy_0,boy_4,0,6]", "X": 1}, { "VarName": "meetsAtEInG[boy_0,boy_5,1,1]", "X": 1}, { "VarName": "meetsAtEInG[boy_0,boy_6,2,0]", "X": 1}, { "VarName": "meetsAtEInG[boy_0,boy_7,2,4]", "X": 1}, { "VarName": "meetsAtEInG[boy_0,boy_8,1,3]", "X": 1}, { "VarName": "meetsAtEInG[boy_0,boy_9,0,6]", "X": 1}, { "VarName": "meetsAtEInG[boy_0,boy_10,0,7]", "X": 1}, { "VarName": "meetsAtEInG[boy_0,boy_10,1,1]", "X": 1}, { "VarName": "meetsAtEInG[boy_0,boy_12,1,2]", "X": 1}, { "VarName": "meetsAtEInG[boy_0,boy_13,2,0]", "X": 1}, { "VarName": "meetsAtEInG[boy_1,boy_3,5,0]", "X": 1}, { "VarName": "meetsAtEInG[boy_1,boy_4,3,2]", "X": 1}, { "VarName": "meetsAtEInG[boy_1,boy_4,5,5]", "X": 1}, { "VarName": "meetsAtEInG[boy_1,boy_5,0,4]", "X": 1}, { "VarName": "meetsAtEInG[boy_1,boy_5,1,1]", "X": 1}, { "VarName": "meetsAtEInG[boy_1,boy_6,3,2]", "X": 1}, { "VarName": "meetsAtEInG[boy_1,boy_7,3,6]", "X": 1}, { "VarName": "meetsAtEInG[boy_1,boy_7,5,0]", "X": 1}, { "VarName": "meetsAtEInG[boy_1,boy_8,1,3]", "X": 1}, { "VarName": "meetsAtEInG[boy_1,boy_8,3,7]", "X": 1}, { "VarName": "meetsAtEInG[boy_1,boy_9,5,0]", "X": 1}, { "VarName": "meetsAtEInG[boy_1,boy_10,1,1]", "X": 1}, { "VarName": "meetsAtEInG[boy_1,boy_11,5,5]", "X": 1}, { "VarName": "meetsAtEInG[boy_1,boy_12,5,0]", "X": 1}, { "VarName": "meetsAtEInG[boy_2,boy_3,1,7]", "X": 1}, { "VarName": "meetsAtEInG[boy_2,boy_4,0,3]", "X": 1}, { "VarName": "meetsAtEInG[boy_2,boy_6,0,5]", "X": 1}, { "VarName": "meetsAtEInG[boy_2,boy_7,2,1]", "X": 1}, { "VarName": "meetsAtEInG[boy_2,boy_7,2,4]", "X": 1}, { "VarName": "meetsAtEInG[boy_2,boy_8,3,0]", "X": 1}, { "VarName": "meetsAtEInG[boy_2,boy_9,1,7]", "X": 1}, { "VarName": "meetsAtEInG[boy_2,boy_10,4,2]", "X": 1}, { "VarName": "meetsAtEInG[boy_2,boy_11,0,3]", "X": 1}, { "VarName": "meetsAtEInG[boy_2,boy_12,0,3]", "X": 1}, { "VarName": "meetsAtEInG[boy_2,boy_12,2,6]", "X": 1}, { "VarName": "meetsAtEInG[boy_2,boy_13,1,7]", "X": 1}, { "VarName": "meetsAtEInG[boy_3,boy_4,1,4]", "X": 1}, { "VarName": "meetsAtEInG[boy_3,boy_5,5,3]", "X": 1}, { "VarName": "meetsAtEInG[boy_3,boy_7,5,0]", "X": 1}, { "VarName": "meetsAtEInG[boy_3,boy_8,4,1]", "X": 1}, { "VarName": "meetsAtEInG[boy_3,boy_9,0,2]", "X": 1}, { "VarName": "meetsAtEInG[boy_3,boy_9,1,7]", "X": 1}, { "VarName": "meetsAtEInG[boy_3,boy_9,5,0]", "X": 1}, { "VarName": "meetsAtEInG[boy_3,boy_10,1,4]", "X": 1}, { "VarName": "meetsAtEInG[boy_3,boy_11,1,6]", "X": 1}, { "VarName": "meetsAtEInG[boy_3,boy_12,5,0]", "X": 1}, { "VarName": "meetsAtEInG[boy_3,boy_13,1,7]", "X": 1}, { "VarName": "meetsAtEInG[boy_4,boy_5,1,0]", "X": 1}, { "VarName": "meetsAtEInG[boy_4,boy_5,2,7]", "X": 1}, { "VarName": "meetsAtEInG[boy_4,boy_6,3,2]", "X": 1}, { "VarName": "meetsAtEInG[boy_4,boy_9,0,6]", "X": 1}, { "VarName": "meetsAtEInG[boy_4,boy_9,5,1]", "X": 1}, { "VarName": "meetsAtEInG[boy_4,boy_10,1,4]", "X": 1}, { "VarName": "meetsAtEInG[boy_4,boy_11,0,3]", "X": 1}, { "VarName": "meetsAtEInG[boy_4,boy_11,5,5]", "X": 1}, { "VarName": "meetsAtEInG[boy_4,boy_12,0,3]", "X": 1}, { "VarName": "meetsAtEInG[boy_5,boy_7,2,2]", "X": 1}, { "VarName": "meetsAtEInG[boy_5,boy_8,2,5]", "X": 1}, { "VarName": "meetsAtEInG[boy_5,boy_10,1,1]", "X": 1}, { "VarName": "meetsAtEInG[boy_5,boy_11,2,2]", "X": 1}, { "VarName": "meetsAtEInG[boy_5,boy_12,2,5]", "X": 1}, { "VarName": "meetsAtEInG[boy_5,boy_13,4,6]", "X": 1}, { "VarName": "meetsAtEInG[boy_6,boy_7,4,3]", "X": 1}, { "VarName": "meetsAtEInG[boy_6,boy_7,4,7]", "X": 1}, { "VarName": "meetsAtEInG[boy_6,boy_8,3,4]", "X": 1}, { "VarName": "meetsAtEInG[boy_6,boy_8,5,6]", "X": 1}, { "VarName": "meetsAtEInG[boy_6,boy_9,4,3]", "X": 1}, { "VarName": "meetsAtEInG[boy_6,boy_10,5,6]", "X": 1}, { "VarName": "meetsAtEInG[boy_6,boy_12,0,1]", "X": 1}, { "VarName": "meetsAtEInG[boy_6,boy_13,2,0]", "X": 1}, { "VarName": "meetsAtEInG[boy_7,boy_9,4,3]", "X": 1}, { "VarName": "meetsAtEInG[boy_7,boy_9,5,0]", "X": 1}, { "VarName": "meetsAtEInG[boy_7,boy_11,2,2]", "X": 1}, { "VarName": "meetsAtEInG[boy_7,boy_12,5,0]", "X": 1}, { "VarName": "meetsAtEInG[boy_7,boy_13,1,5]", "X": 1}, { "VarName": "meetsAtEInG[boy_8,boy_10,5,6]", "X": 1}, { "VarName": "meetsAtEInG[boy_8,boy_12,2,5]", "X": 1}, { "VarName": "meetsAtEInG[boy_8,boy_13,5,2]", "X": 1}, { "VarName": "meetsAtEInG[boy_9,boy_10,4,5]", "X": 1}, { "VarName": "meetsAtEInG[boy_9,boy_11,5,4]", "X": 1}, { "VarName": "meetsAtEInG[boy_9,boy_12,5,0]", "X": 1}, { "VarName": "meetsAtEInG[boy_9,boy_13,1,7]", "X": 1}, { "VarName": "meetsAtEInG[boy_10,boy_11,0,0]", "X": 1}, { "VarName": "meetsAtEInG[boy_10,boy_13,3,3]", "X": 1}, { "VarName": "meetsAtEInG[boy_11,boy_12,0,3]", "X": 1}, { "VarName": "meetsAtEInG[boy_11,boy_12,5,7]", "X": 1}, { "VarName": "meetsAtEInG[boy_11,boy_13,3,1]", "X": 1}, { "VarName": "meetsAtEInG[boy_12,boy_13,4,4]", "X": 1}, { "VarName": "isInGroupAtE[girl_0,0,7]", "X": 1}, { "VarName": "isInGroupAtE[girl_0,1,4]", "X": 1}, { "VarName": "isInGroupAtE[girl_0,2,0]", "X": 1}, { "VarName": "isInGroupAtE[girl_0,2,3]", "X": 1}, { "VarName": "isInGroupAtE[girl_0,2,5]", "X": 1}, { "VarName": "isInGroupAtE[girl_0,3,6]", "X": 1}, { "VarName": "isInGroupAtE[girl_0,4,2]", "X": 1}, { "VarName": "isInGroupAtE[girl_0,5,1]", "X": 1}, { "VarName": "isInGroupAtE[girl_1,0,1]", "X": 1}, { "VarName": "isInGroupAtE[girl_1,1,3]", "X": 1}, { "VarName": "isInGroupAtE[girl_1,1,5]", "X": 1}, { "VarName": "isInGroupAtE[girl_1,2,7]", "X": 1}, { "VarName": "isInGroupAtE[girl_1,4,0]", "X": 1}, { "VarName": "isInGroupAtE[girl_1,4,2]", "X": 1}, { "VarName": "isInGroupAtE[girl_1,5,4]", "X": 1}, { "VarName": "isInGroupAtE[girl_1,5,6]", "X": 1}, { "VarName": "isInGroupAtE[girl_2,0,2]", "X": 1}, { "VarName": "isInGroupAtE[girl_2,0,7]", "X": 1}, { "VarName": "isInGroupAtE[girl_2,1,0]", "X": 1}, { "VarName": "isInGroupAtE[girl_2,1,3]", "X": 1}, { "VarName": "isInGroupAtE[girl_2,2,6]", "X": 1}, { "VarName": "isInGroupAtE[girl_2,3,1]", "X": 1}, { "VarName": "isInGroupAtE[girl_2,4,4]", "X": 1}, { "VarName": "isInGroupAtE[girl_2,5,5]", "X": 1}, { "VarName": "isInGroupAtE[girl_3,0,0]", "X": 1}, { "VarName": "isInGroupAtE[girl_3,0,2]", "X": 1}, { "VarName": "isInGroupAtE[girl_3,0,6]", "X": 1}, { "VarName": "isInGroupAtE[girl_3,1,5]", "X": 1}, { "VarName": "isInGroupAtE[girl_3,2,1]", "X": 1}, { "VarName": "isInGroupAtE[girl_3,2,3]", "X": 1}, { "VarName": "isInGroupAtE[girl_3,3,4]", "X": 1}, { "VarName": "isInGroupAtE[girl_3,5,7]", "X": 1}, { "VarName": "isInGroupAtE[girl_4,0,5]", "X": 1}, { "VarName": "isInGroupAtE[girl_4,1,2]", "X": 1}, { "VarName": "isInGroupAtE[girl_4,1,4]", "X": 1}, { "VarName": "isInGroupAtE[girl_4,3,1]", "X": 1}, { "VarName": "isInGroupAtE[girl_4,3,7]", "X": 1}, { "VarName": "isInGroupAtE[girl_4,4,0]", "X": 1}, { "VarName": "isInGroupAtE[girl_4,4,3]", "X": 1}, { "VarName": "isInGroupAtE[girl_4,4,6]", "X": 1}, { "VarName": "isInGroupAtE[girl_5,2,0]", "X": 1}, { "VarName": "isInGroupAtE[girl_5,2,2]", "X": 1}, { "VarName": "isInGroupAtE[girl_5,2,3]", "X": 1}, { "VarName": "isInGroupAtE[girl_5,2,4]", "X": 1}, { "VarName": "isInGroupAtE[girl_5,2,6]", "X": 1}, { "VarName": "isInGroupAtE[girl_5,2,7]", "X": 1}, { "VarName": "isInGroupAtE[girl_5,4,1]", "X": 1}, { "VarName": "isInGroupAtE[girl_5,4,5]", "X": 1}, { "VarName": "isInGroupAtE[girl_6,0,7]", "X": 1}, { "VarName": "isInGroupAtE[girl_6,1,6]", "X": 1}, { "VarName": "isInGroupAtE[girl_6,2,1]", "X": 1}, { "VarName": "isInGroupAtE[girl_6,3,2]", "X": 1}, { "VarName": "isInGroupAtE[girl_6,4,0]", "X": 1}, { "VarName": "isInGroupAtE[girl_6,4,4]", "X": 1}, { "VarName": "isInGroupAtE[girl_6,4,5]", "X": 1}, { "VarName": "isInGroupAtE[girl_6,5,3]", "X": 1}, { "VarName": "isInGroupAtE[girl_7,2,4]", "X": 1}, { "VarName": "isInGroupAtE[girl_7,3,0]", "X": 1}, { "VarName": "isInGroupAtE[girl_7,5,1]", "X": 1}, { "VarName": "isInGroupAtE[girl_7,5,2]", "X": 1}, { "VarName": "isInGroupAtE[girl_7,5,3]", "X": 1}, { "VarName": "isInGroupAtE[girl_7,5,5]", "X": 1}, { "VarName": "isInGroupAtE[girl_7,5,6]", "X": 1}, { "VarName": "isInGroupAtE[girl_7,5,7]", "X": 1}, { "VarName": "isInGroupAtE[girl_8,0,4]", "X": 1}, { "VarName": "isInGroupAtE[girl_8,1,0]", "X": 1}, { "VarName": "isInGroupAtE[girl_8,3,5]", "X": 1}, { "VarName": "isInGroupAtE[girl_8,4,1]", "X": 1}, { "VarName": "isInGroupAtE[girl_8,4,2]", "X": 1}, { "VarName": "isInGroupAtE[girl_8,4,3]", "X": 1}, { "VarName": "isInGroupAtE[girl_8,4,6]", "X": 1}, { "VarName": "isInGroupAtE[girl_8,5,7]", "X": 1}, { "VarName": "isInGroupAtE[girl_9,0,0]", "X": 1}, { "VarName": "isInGroupAtE[girl_9,0,1]", "X": 1}, { "VarName": "isInGroupAtE[girl_9,0,4]", "X": 1}, { "VarName": "isInGroupAtE[girl_9,0,5]", "X": 1}, { "VarName": "isInGroupAtE[girl_9,0,6]", "X": 1}, { "VarName": "isInGroupAtE[girl_9,2,3]", "X": 1}, { "VarName": "isInGroupAtE[girl_9,4,7]", "X": 1}, { "VarName": "isInGroupAtE[girl_9,5,2]", "X": 1}, { "VarName": "isInGroupAtE[girl_10,1,0]", "X": 1}, { "VarName": "isInGroupAtE[girl_10,1,2]", "X": 1}, { "VarName": "isInGroupAtE[girl_10,1,6]", "X": 1}, { "VarName": "isInGroupAtE[girl_10,2,1]", "X": 1}, { "VarName": "isInGroupAtE[girl_10,2,5]", "X": 1}, { "VarName": "isInGroupAtE[girl_10,3,3]", "X": 1}, { "VarName": "isInGroupAtE[girl_10,4,7]", "X": 1}, { "VarName": "isInGroupAtE[girl_10,5,4]", "X": 1}, { "VarName": "isInGroupAtE[girl_11,2,2]", "X": 1}, { "VarName": "isInGroupAtE[girl_11,2,6]", "X": 1}, { "VarName": "isInGroupAtE[girl_11,3,3]", "X": 1}, { "VarName": "isInGroupAtE[girl_11,3,4]", "X": 1}, { "VarName": "isInGroupAtE[girl_11,3,5]", "X": 1}, { "VarName": "isInGroupAtE[girl_11,3,7]", "X": 1}, { "VarName": "isInGroupAtE[girl_11,4,0]", "X": 1}, { "VarName": "isInGroupAtE[girl_11,5,1]", "X": 1}, { "VarName": "isInGroupAtE[girl_12,0,4]", "X": 1}, { "VarName": "isInGroupAtE[girl_12,2,7]", "X": 1}, { "VarName": "isInGroupAtE[girl_12,3,0]", "X": 1}, { "VarName": "isInGroupAtE[girl_12,3,1]", "X": 1}, { "VarName": "isInGroupAtE[girl_12,3,2]", "X": 1}, { "VarName": "isInGroupAtE[girl_12,3,3]", "X": 1}, { "VarName": "isInGroupAtE[girl_12,3,6]", "X": 1}, { "VarName": "isInGroupAtE[girl_12,4,5]", "X": 1}, { "VarName": "isInGroupAtE[boy_0,0,6]", "X": 1}, { "VarName": "isInGroupAtE[boy_0,0,7]", "X": 1}, { "VarName": "isInGroupAtE[boy_0,1,1]", "X": 1}, { "VarName": "isInGroupAtE[boy_0,1,2]", "X": 1}, { "VarName": "isInGroupAtE[boy_0,1,3]", "X": 1}, { "VarName": "isInGroupAtE[boy_0,2,0]", "X": 1}, { "VarName": "isInGroupAtE[boy_0,2,4]", "X": 1}, { "VarName": "isInGroupAtE[boy_0,3,5]", "X": 1}, { "VarName": "isInGroupAtE[boy_1,0,4]", "X": 1}, { "VarName": "isInGroupAtE[boy_1,1,1]", "X": 1}, { "VarName": "isInGroupAtE[boy_1,1,3]", "X": 1}, { "VarName": "isInGroupAtE[boy_1,3,2]", "X": 1}, { "VarName": "isInGroupAtE[boy_1,3,6]", "X": 1}, { "VarName": "isInGroupAtE[boy_1,3,7]", "X": 1}, { "VarName": "isInGroupAtE[boy_1,5,0]", "X": 1}, { "VarName": "isInGroupAtE[boy_1,5,5]", "X": 1}, { "VarName": "isInGroupAtE[boy_2,0,3]", "X": 1}, { "VarName": "isInGroupAtE[boy_2,0,5]", "X": 1}, { "VarName": "isInGroupAtE[boy_2,1,7]", "X": 1}, { "VarName": "isInGroupAtE[boy_2,2,1]", "X": 1}, { "VarName": "isInGroupAtE[boy_2,2,4]", "X": 1}, { "VarName": "isInGroupAtE[boy_2,2,6]", "X": 1}, { "VarName": "isInGroupAtE[boy_2,3,0]", "X": 1}, { "VarName": "isInGroupAtE[boy_2,4,2]", "X": 1}, { "VarName": "isInGroupAtE[boy_3,0,2]", "X": 1}, { "VarName": "isInGroupAtE[boy_3,1,4]", "X": 1}, { "VarName": "isInGroupAtE[boy_3,1,6]", "X": 1}, { "VarName": "isInGroupAtE[boy_3,1,7]", "X": 1}, { "VarName": "isInGroupAtE[boy_3,3,5]", "X": 1}, { "VarName": "isInGroupAtE[boy_3,4,1]", "X": 1}, { "VarName": "isInGroupAtE[boy_3,5,0]", "X": 1}, { "VarName": "isInGroupAtE[boy_3,5,3]", "X": 1}, { "VarName": "isInGroupAtE[boy_4,0,3]", "X": 1}, { "VarName": "isInGroupAtE[boy_4,0,6]", "X": 1}, { "VarName": "isInGroupAtE[boy_4,1,0]", "X": 1}, { "VarName": "isInGroupAtE[boy_4,1,4]", "X": 1}, { "VarName": "isInGroupAtE[boy_4,2,7]", "X": 1}, { "VarName": "isInGroupAtE[boy_4,3,2]", "X": 1}, { "VarName": "isInGroupAtE[boy_4,5,1]", "X": 1}, { "VarName": "isInGroupAtE[boy_4,5,5]", "X": 1}, { "VarName": "isInGroupAtE[boy_5,0,4]", "X": 1}, { "VarName": "isInGroupAtE[boy_5,1,0]", "X": 1}, { "VarName": "isInGroupAtE[boy_5,1,1]", "X": 1}, { "VarName": "isInGroupAtE[boy_5,2,2]", "X": 1}, { "VarName": "isInGroupAtE[boy_5,2,5]", "X": 1}, { "VarName": "isInGroupAtE[boy_5,2,7]", "X": 1}, { "VarName": "isInGroupAtE[boy_5,4,6]", "X": 1}, { "VarName": "isInGroupAtE[boy_5,5,3]", "X": 1}, { "VarName": "isInGroupAtE[boy_6,0,1]", "X": 1}, { "VarName": "isInGroupAtE[boy_6,0,5]", "X": 1}, { "VarName": "isInGroupAtE[boy_6,2,0]", "X": 1}, { "VarName": "isInGroupAtE[boy_6,3,2]", "X": 1}, { "VarName": "isInGroupAtE[boy_6,3,4]", "X": 1}, { "VarName": "isInGroupAtE[boy_6,4,3]", "X": 1}, { "VarName": "isInGroupAtE[boy_6,4,7]", "X": 1}, { "VarName": "isInGroupAtE[boy_6,5,6]", "X": 1}, { "VarName": "isInGroupAtE[boy_7,1,5]", "X": 1}, { "VarName": "isInGroupAtE[boy_7,2,1]", "X": 1}, { "VarName": "isInGroupAtE[boy_7,2,2]", "X": 1}, { "VarName": "isInGroupAtE[boy_7,2,4]", "X": 1}, { "VarName": "isInGroupAtE[boy_7,3,6]", "X": 1}, { "VarName": "isInGroupAtE[boy_7,4,3]", "X": 1}, { "VarName": "isInGroupAtE[boy_7,4,7]", "X": 1}, { "VarName": "isInGroupAtE[boy_7,5,0]", "X": 1}, { "VarName": "isInGroupAtE[boy_8,1,3]", "X": 1}, { "VarName": "isInGroupAtE[boy_8,2,5]", "X": 1}, { "VarName": "isInGroupAtE[boy_8,3,0]", "X": 1}, { "VarName": "isInGroupAtE[boy_8,3,4]", "X": 1}, { "VarName": "isInGroupAtE[boy_8,3,7]", "X": 1}, { "VarName": "isInGroupAtE[boy_8,4,1]", "X": 1}, { "VarName": "isInGroupAtE[boy_8,5,2]", "X": 1}, { "VarName": "isInGroupAtE[boy_8,5,6]", "X": 1}, { "VarName": "isInGroupAtE[boy_9,0,2]", "X": 1}, { "VarName": "isInGroupAtE[boy_9,0,6]", "X": 1}, { "VarName": "isInGroupAtE[boy_9,1,7]", "X": 1}, { "VarName": "isInGroupAtE[boy_9,4,3]", "X": 1}, { "VarName": "isInGroupAtE[boy_9,4,5]", "X": 1}, { "VarName": "isInGroupAtE[boy_9,5,0]", "X": 1}, { "VarName": "isInGroupAtE[boy_9,5,1]", "X": 1}, { "VarName": "isInGroupAtE[boy_9,5,4]", "X": 1}, { "VarName": "isInGroupAtE[boy_10,0,0]", "X": 1}, { "VarName": "isInGroupAtE[boy_10,0,7]", "X": 1}, { "VarName": "isInGroupAtE[boy_10,1,1]", "X": 1}, { "VarName": "isInGroupAtE[boy_10,1,4]", "X": 1}, { "VarName": "isInGroupAtE[boy_10,3,3]", "X": 1}, { "VarName": "isInGroupAtE[boy_10,4,2]", "X": 1}, { "VarName": "isInGroupAtE[boy_10,4,5]", "X": 1}, { "VarName": "isInGroupAtE[boy_10,5,6]", "X": 1}, { "VarName": "isInGroupAtE[boy_11,0,0]", "X": 1}, { "VarName": "isInGroupAtE[boy_11,0,3]", "X": 1}, { "VarName": "isInGroupAtE[boy_11,1,6]", "X": 1}, { "VarName": "isInGroupAtE[boy_11,2,2]", "X": 1}, { "VarName": "isInGroupAtE[boy_11,3,1]", "X": 1}, { "VarName": "isInGroupAtE[boy_11,5,4]", "X": 1}, { "VarName": "isInGroupAtE[boy_11,5,5]", "X": 1}, { "VarName": "isInGroupAtE[boy_11,5,7]", "X": 1}, { "VarName": "isInGroupAtE[boy_12,0,1]", "X": 1}, { "VarName": "isInGroupAtE[boy_12,0,3]", "X": 1}, { "VarName": "isInGroupAtE[boy_12,1,2]", "X": 1}, { "VarName": "isInGroupAtE[boy_12,2,5]", "X": 1}, { "VarName": "isInGroupAtE[boy_12,2,6]", "X": 1}, { "VarName": "isInGroupAtE[boy_12,4,4]", "X": 1}, { "VarName": "isInGroupAtE[boy_12,5,0]", "X": 1}, { "VarName": "isInGroupAtE[boy_12,5,7]", "X": 1}, { "VarName": "isInGroupAtE[boy_13,1,5]", "X": 1}, { "VarName": "isInGroupAtE[boy_13,1,7]", "X": 1}, { "VarName": "isInGroupAtE[boy_13,2,0]", "X": 1}, { "VarName": "isInGroupAtE[boy_13,3,1]", "X": 1}, { "VarName": "isInGroupAtE[boy_13,3,3]", "X": 1}, { "VarName": "isInGroupAtE[boy_13,4,4]", "X": 1}, { "VarName": "isInGroupAtE[boy_13,4,6]", "X": 1}, { "VarName": "isInGroupAtE[boy_13,5,2]", "X": 1}, { "VarName": "groupInUse[0,0]", "X": 1}, { "VarName": "groupInUse[0,1]", "X": 1}, { "VarName": "groupInUse[0,2]", "X": 1}, { "VarName": "groupInUse[0,3]", "X": 1}, { "VarName": "groupInUse[0,4]", "X": 1}, { "VarName": "groupInUse[0,5]", "X": 1}, { "VarName": "groupInUse[0,6]", "X": 1}, { "VarName": "groupInUse[0,7]", "X": 1}, { "VarName": "groupInUse[1,0]", "X": 1}, { "VarName": "groupInUse[1,1]", "X": 1}, { "VarName": "groupInUse[1,2]", "X": 1}, { "VarName": "groupInUse[1,3]", "X": 1}, { "VarName": "groupInUse[1,4]", "X": 1}, { "VarName": "groupInUse[1,5]", "X": 1}, { "VarName": "groupInUse[1,6]", "X": 1}, { "VarName": "groupInUse[1,7]", "X": 1}, { "VarName": "groupInUse[2,0]", "X": 1}, { "VarName": "groupInUse[2,1]", "X": 1}, { "VarName": "groupInUse[2,2]", "X": 1}, { "VarName": "groupInUse[2,3]", "X": 1}, { "VarName": "groupInUse[2,4]", "X": 1}, { "VarName": "groupInUse[2,5]", "X": 1}, { "VarName": "groupInUse[2,6]", "X": 1}, { "VarName": "groupInUse[2,7]", "X": 1}, { "VarName": "groupInUse[3,0]", "X": 1}, { "VarName": "groupInUse[3,1]", "X": 1}, { "VarName": "groupInUse[3,2]", "X": 1}, { "VarName": "groupInUse[3,3]", "X": 1}, { "VarName": "groupInUse[3,4]", "X": 1}, { "VarName": "groupInUse[3,5]", "X": 1}, { "VarName": "groupInUse[3,6]", "X": 1}, { "VarName": "groupInUse[3,7]", "X": 1}, { "VarName": "groupInUse[4,0]", "X": 1}, { "VarName": "groupInUse[4,1]", "X": 1}, { "VarName": "groupInUse[4,2]", "X": 1}, { "VarName": "groupInUse[4,3]", "X": 1}, { "VarName": "groupInUse[4,4]", "X": 1}, { "VarName": "groupInUse[4,5]", "X": 1}, { "VarName": "groupInUse[4,6]", "X": 1}, { "VarName": "groupInUse[4,7]", "X": 1}, { "VarName": "groupInUse[5,0]", "X": 1}, { "VarName": "groupInUse[5,1]", "X": 1}, { "VarName": "groupInUse[5,2]", "X": 1}, { "VarName": "groupInUse[5,3]", "X": 1}, { "VarName": "groupInUse[5,4]", "X": 1}, { "VarName": "groupInUse[5,5]", "X": 1}, { "VarName": "groupInUse[5,6]", "X": 1}, { "VarName": "groupInUse[5,7]", "X": 1}, { "VarName": "visits[girl_0,girl_3,3]", "X": 1}, { "VarName": "visits[girl_0,girl_5,3]", "X": 1}, { "VarName": "visits[girl_0,girl_9,3]", "X": 1}, { "VarName": "visits[girl_1,girl_5,7]", "X": 1}, { "VarName": "visits[girl_1,girl_12,7]", "X": 1}, { "VarName": "visits[girl_1,boy_4,7]", "X": 1}, { "VarName": "visits[girl_1,boy_5,7]", "X": 1}, { "VarName": "visits[girl_2,girl_1,3]", "X": 1}, { "VarName": "visits[girl_2,girl_7,5]", "X": 1}, { "VarName": "visits[girl_2,girl_8,0]", "X": 1}, { "VarName": "visits[girl_2,girl_10,0]", "X": 1}, { "VarName": "visits[girl_2,boy_0,3]", "X": 1}, { "VarName": "visits[girl_2,boy_1,3]", "X": 1}, { "VarName": "visits[girl_2,boy_1,5]", "X": 1}, { "VarName": "visits[girl_2,boy_4,0]", "X": 1}, { "VarName": "visits[girl_2,boy_4,5]", "X": 1}, { "VarName": "visits[girl_2,boy_5,0]", "X": 1}, { "VarName": "visits[girl_2,boy_8,3]", "X": 1}, { "VarName": "visits[girl_2,boy_11,5]", "X": 1}, { "VarName": "visits[girl_3,girl_1,5]", "X": 1}, { "VarName": "visits[girl_3,girl_2,2]", "X": 1}, { "VarName": "visits[girl_3,girl_7,7]", "X": 1}, { "VarName": "visits[girl_3,girl_8,7]", "X": 1}, { "VarName": "visits[girl_3,boy_3,2]", "X": 1}, { "VarName": "visits[girl_3,boy_7,5]", "X": 1}, { "VarName": "visits[girl_3,boy_9,2]", "X": 1}, { "VarName": "visits[girl_3,boy_11,7]", "X": 1}, { "VarName": "visits[girl_3,boy_12,7]", "X": 1}, { "VarName": "visits[girl_3,boy_13,5]", "X": 1}, { "VarName": "visits[girl_5,girl_7,4]", "X": 1}, { "VarName": "visits[girl_5,boy_0,4]", "X": 1}, { "VarName": "visits[girl_5,boy_2,4]", "X": 1}, { "VarName": "visits[girl_5,boy_7,4]", "X": 1}, { "VarName": "visits[girl_6,girl_1,0]", "X": 1}, { "VarName": "visits[girl_6,girl_4,0]", "X": 1}, { "VarName": "visits[girl_6,girl_5,5]", "X": 1}, { "VarName": "visits[girl_6,girl_7,3]", "X": 1}, { "VarName": "visits[girl_6,girl_11,0]", "X": 1}, { "VarName": "visits[girl_6,girl_12,5]", "X": 1}, { "VarName": "visits[girl_6,boy_3,3]", "X": 1}, { "VarName": "visits[girl_6,boy_5,3]", "X": 1}, { "VarName": "visits[girl_6,boy_9,5]", "X": 1}, { "VarName": "visits[girl_6,boy_10,5]", "X": 1}, { "VarName": "visits[girl_7,girl_1,6]", "X": 1}, { "VarName": "visits[girl_7,girl_12,0]", "X": 1}, { "VarName": "visits[girl_7,boy_2,0]", "X": 1}, { "VarName": "visits[girl_7,boy_6,6]", "X": 1}, { "VarName": "visits[girl_7,boy_8,0]", "X": 1}, { "VarName": "visits[girl_7,boy_8,6]", "X": 1}, { "VarName": "visits[girl_7,boy_10,6]", "X": 1}, { "VarName": "visits[girl_8,girl_0,2]", "X": 1}, { "VarName": "visits[girl_8,girl_1,2]", "X": 1}, { "VarName": "visits[girl_8,girl_11,5]", "X": 1}, { "VarName": "visits[girl_8,boy_0,5]", "X": 1}, { "VarName": "visits[girl_8,boy_2,2]", "X": 1}, { "VarName": "visits[girl_8,boy_3,5]", "X": 1}, { "VarName": "visits[girl_8,boy_10,2]", "X": 1}, { "VarName": "visits[girl_9,girl_3,6]", "X": 1}, { "VarName": "visits[girl_9,boy_0,6]", "X": 1}, { "VarName": "visits[girl_9,boy_4,6]", "X": 1}, { "VarName": "visits[girl_9,boy_9,6]", "X": 1}, { "VarName": "visits[girl_10,girl_4,2]", "X": 1}, { "VarName": "visits[girl_10,girl_9,7]", "X": 1}, { "VarName": "visits[girl_10,boy_0,2]", "X": 1}, { "VarName": "visits[girl_10,boy_6,7]", "X": 1}, { "VarName": "visits[girl_10,boy_7,7]", "X": 1}, { "VarName": "visits[girl_10,boy_12,2]", "X": 1}, { "VarName": "visits[girl_11,girl_2,6]", "X": 1}, { "VarName": "visits[girl_11,girl_5,6]", "X": 1}, { "VarName": "visits[girl_11,girl_10,3]", "X": 1}, { "VarName": "visits[girl_11,girl_12,3]", "X": 1}, { "VarName": "visits[girl_11,boy_2,6]", "X": 1}, { "VarName": "visits[girl_11,boy_10,3]", "X": 1}, { "VarName": "visits[girl_11,boy_12,6]", "X": 1}, { "VarName": "visits[girl_11,boy_13,3]", "X": 1}, { "VarName": "visits[girl_12,girl_2,1]", "X": 1}, { "VarName": "visits[girl_12,girl_4,1]", "X": 1}, { "VarName": "visits[girl_12,girl_8,4]", "X": 1}, { "VarName": "visits[girl_12,girl_9,4]", "X": 1}, { "VarName": "visits[girl_12,boy_1,4]", "X": 1}, { "VarName": "visits[girl_12,boy_5,4]", "X": 1}, { "VarName": "visits[girl_12,boy_11,1]", "X": 1}, { "VarName": "visits[girl_12,boy_13,1]", "X": 1}, { "VarName": "visits[boy_0,girl_0,0]", "X": 1}, { "VarName": "visits[boy_0,girl_0,7]", "X": 1}, { "VarName": "visits[boy_0,girl_2,7]", "X": 1}, { "VarName": "visits[boy_0,girl_5,0]", "X": 1}, { "VarName": "visits[boy_0,girl_6,7]", "X": 1}, { "VarName": "visits[boy_0,boy_6,0]", "X": 1}, { "VarName": "visits[boy_0,boy_10,7]", "X": 1}, { "VarName": "visits[boy_0,boy_13,0]", "X": 1}, { "VarName": "visits[boy_1,girl_0,6]", "X": 1}, { "VarName": "visits[boy_1,girl_12,6]", "X": 1}, { "VarName": "visits[boy_1,boy_3,0]", "X": 1}, { "VarName": "visits[boy_1,boy_7,0]", "X": 1}, { "VarName": "visits[boy_1,boy_7,6]", "X": 1}, { "VarName": "visits[boy_1,boy_9,0]", "X": 1}, { "VarName": "visits[boy_1,boy_12,0]", "X": 1}, { "VarName": "visits[boy_2,girl_4,5]", "X": 1}, { "VarName": "visits[boy_2,girl_9,5]", "X": 1}, { "VarName": "visits[boy_2,boy_6,5]", "X": 1}, { "VarName": "visits[boy_3,girl_6,6]", "X": 1}, { "VarName": "visits[boy_3,girl_10,6]", "X": 1}, { "VarName": "visits[boy_3,boy_11,6]", "X": 1}, { "VarName": "visits[boy_4,girl_0,1]", "X": 1}, { "VarName": "visits[boy_4,girl_0,4]", "X": 1}, { "VarName": "visits[boy_4,girl_4,4]", "X": 1}, { "VarName": "visits[boy_4,girl_7,1]", "X": 1}, { "VarName": "visits[boy_4,girl_11,1]", "X": 1}, { "VarName": "visits[boy_4,boy_3,4]", "X": 1}, { "VarName": "visits[boy_4,boy_9,1]", "X": 1}, { "VarName": "visits[boy_4,boy_10,4]", "X": 1}, { "VarName": "visits[boy_5,girl_4,6]", "X": 1}, { "VarName": "visits[boy_5,girl_8,6]", "X": 1}, { "VarName": "visits[boy_5,boy_13,6]", "X": 1}, { "VarName": "visits[boy_6,girl_3,4]", "X": 1}, { "VarName": "visits[boy_6,girl_6,2]", "X": 1}, { "VarName": "visits[boy_6,girl_11,4]", "X": 1}, { "VarName": "visits[boy_6,girl_12,2]", "X": 1}, { "VarName": "visits[boy_6,boy_1,2]", "X": 1}, { "VarName": "visits[boy_6,boy_4,2]", "X": 1}, { "VarName": "visits[boy_6,boy_8,4]", "X": 1}, { "VarName": "visits[boy_7,girl_3,1]", "X": 1}, { "VarName": "visits[boy_7,girl_4,3]", "X": 1}, { "VarName": "visits[boy_7,girl_6,1]", "X": 1}, { "VarName": "visits[boy_7,girl_8,3]", "X": 1}, { "VarName": "visits[boy_7,girl_10,1]", "X": 1}, { "VarName": "visits[boy_7,boy_2,1]", "X": 1}, { "VarName": "visits[boy_7,boy_6,3]", "X": 1}, { "VarName": "visits[boy_7,boy_9,3]", "X": 1}, { "VarName": "visits[boy_8,girl_4,7]", "X": 1}, { "VarName": "visits[boy_8,girl_5,1]", "X": 1}, { "VarName": "visits[boy_8,girl_8,1]", "X": 1}, { "VarName": "visits[boy_8,girl_11,7]", "X": 1}, { "VarName": "visits[boy_8,boy_1,7]", "X": 1}, { "VarName": "visits[boy_8,boy_3,1]", "X": 1}, { "VarName": "visits[boy_10,boy_0,1]", "X": 1}, { "VarName": "visits[boy_10,boy_1,1]", "X": 1}, { "VarName": "visits[boy_10,boy_5,1]", "X": 1}, { "VarName": "visits[boy_11,girl_1,4]", "X": 1}, { "VarName": "visits[boy_11,girl_3,0]", "X": 1}, { "VarName": "visits[boy_11,girl_5,2]", "X": 1}, { "VarName": "visits[boy_11,girl_9,0]", "X": 1}, { "VarName": "visits[boy_11,girl_10,4]", "X": 1}, { "VarName": "visits[boy_11,girl_11,2]", "X": 1}, { "VarName": "visits[boy_11,boy_5,2]", "X": 1}, { "VarName": "visits[boy_11,boy_7,2]", "X": 1}, { "VarName": "visits[boy_11,boy_9,4]", "X": 1}, { "VarName": "visits[boy_11,boy_10,0]", "X": 1}, { "VarName": "visits[boy_12,girl_0,5]", "X": 1}, { "VarName": "visits[boy_12,girl_1,1]", "X": 1}, { "VarName": "visits[boy_12,girl_9,1]", "X": 1}, { "VarName": "visits[boy_12,girl_10,5]", "X": 1}, { "VarName": "visits[boy_12,boy_2,3]", "X": 1}, { "VarName": "visits[boy_12,boy_4,3]", "X": 1}, { "VarName": "visits[boy_12,boy_5,5]", "X": 1}, { "VarName": "visits[boy_12,boy_6,1]", "X": 1}, { "VarName": "visits[boy_12,boy_8,5]", "X": 1}, { "VarName": "visits[boy_12,boy_11,3]", "X": 1}, { "VarName": "visits[boy_13,girl_2,4]", "X": 1}, { "VarName": "visits[boy_13,girl_6,4]", "X": 1}, { "VarName": "visits[boy_13,girl_7,2]", "X": 1}, { "VarName": "visits[boy_13,girl_9,2]", "X": 1}, { "VarName": "visits[boy_13,boy_2,7]", "X": 1}, { "VarName": "visits[boy_13,boy_3,7]", "X": 1}, { "VarName": "visits[boy_13,boy_8,2]", "X": 1}, { "VarName": "visits[boy_13,boy_9,7]", "X": 1}, { "VarName": "visits[boy_13,boy_12,4]", "X": 1}, { "VarName": "isHost[girl_0,3]", "X": 1}, { "VarName": "isHost[girl_1,7]", "X": 1}, { "VarName": "isHost[girl_2,0]", "X": 1}, { "VarName": "isHost[girl_2,3]", "X": 1}, { "VarName": "isHost[girl_2,5]", "X": 1}, { "VarName": "isHost[girl_3,2]", "X": 1}, { "VarName": "isHost[girl_3,5]", "X": 1}, { "VarName": "isHost[girl_3,7]", "X": 1}, { "VarName": "isHost[girl_5,4]", "X": 1}, { "VarName": "isHost[girl_6,0]", "X": 1}, { "VarName": "isHost[girl_6,3]", "X": 1}, { "VarName": "isHost[girl_6,5]", "X": 1}, { "VarName": "isHost[girl_7,0]", "X": 1}, { "VarName": "isHost[girl_7,6]", "X": 1}, { "VarName": "isHost[girl_8,2]", "X": 1}, { "VarName": "isHost[girl_8,5]", "X": 1}, { "VarName": "isHost[girl_9,6]", "X": 1}, { "VarName": "isHost[girl_10,2]", "X": 1}, { "VarName": "isHost[girl_10,7]", "X": 1}, { "VarName": "isHost[girl_11,3]", "X": 1}, { "VarName": "isHost[girl_11,6]", "X": 1}, { "VarName": "isHost[girl_12,1]", "X": 1}, { "VarName": "isHost[girl_12,4]", "X": 1}, { "VarName": "isHost[boy_0,0]", "X": 1}, { "VarName": "isHost[boy_0,7]", "X": 1}, { "VarName": "isHost[boy_1,0]", "X": 1}, { "VarName": "isHost[boy_1,6]", "X": 1}, { "VarName": "isHost[boy_2,5]", "X": 1}, { "VarName": "isHost[boy_3,6]", "X": 1}, { "VarName": "isHost[boy_4,1]", "X": 1}, { "VarName": "isHost[boy_4,4]", "X": 1}, { "VarName": "isHost[boy_5,6]", "X": 1}, { "VarName": "isHost[boy_6,2]", "X": 1}, { "VarName": "isHost[boy_6,4]", "X": 1}, { "VarName": "isHost[boy_7,1]", "X": 1}, { "VarName": "isHost[boy_7,3]", "X": 1}, { "VarName": "isHost[boy_8,1]", "X": 1}, { "VarName": "isHost[boy_8,7]", "X": 1}, { "VarName": "isHost[boy_10,1]", "X": 1}, { "VarName": "isHost[boy_11,0]", "X": 1}, { "VarName": "isHost[boy_11,2]", "X": 1}, { "VarName": "isHost[boy_11,4]", "X": 1}, { "VarName": "isHost[boy_12,1]", "X": 1}, { "VarName": "isHost[boy_12,3]", "X": 1}, { "VarName": "isHost[boy_12,5]", "X": 1}, { "VarName": "isHost[boy_13,2]", "X": 1}, { "VarName": "isHost[boy_13,4]", "X": 1}, { "VarName": "isHost[boy_13,7]", "X": 1}]}